{
"meta":{"test_sets":[],"test_metrics":[],"learn_metrics":[{"best_value":"Min","name":"RMSE"}],"launch_mode":"Train","parameters":"","iteration_count":1000,"learn_sets":["learn"],"name":"experiment"},
"iterations":[
{"learn":[10.4652796],"iteration":0,"passed_time":0.001305240166,"remaining_time":1.303934926},
{"learn":[10.33380691],"iteration":1,"passed_time":0.002749961544,"remaining_time":1.37223081},
{"learn":[10.21593759],"iteration":2,"passed_time":0.004005088351,"remaining_time":1.331024362},
{"learn":[10.09977052],"iteration":3,"passed_time":0.005395935544,"remaining_time":1.34358795},
{"learn":[9.982957011],"iteration":4,"passed_time":0.006723951704,"remaining_time":1.338066389},
{"learn":[9.873998973],"iteration":5,"passed_time":0.008157609739,"remaining_time":1.351444013},
{"learn":[9.770365193],"iteration":6,"passed_time":0.009640413149,"remaining_time":1.367561465},
{"learn":[9.669413322],"iteration":7,"passed_time":0.0110151742,"remaining_time":1.365881601},
{"learn":[9.57286411],"iteration":8,"passed_time":0.01236813728,"remaining_time":1.361869339},
{"learn":[9.48687718],"iteration":9,"passed_time":0.01374248321,"remaining_time":1.360505838},
{"learn":[9.406124877],"iteration":10,"passed_time":0.01517301276,"remaining_time":1.364191783},
{"learn":[9.328301151],"iteration":11,"passed_time":0.01618071785,"remaining_time":1.332212436},
{"learn":[9.248783659],"iteration":12,"passed_time":0.017596125,"remaining_time":1.335951952},
{"learn":[9.179819499],"iteration":13,"passed_time":0.01897295011,"remaining_time":1.336237772},
{"learn":[9.111809655],"iteration":14,"passed_time":0.02036858553,"remaining_time":1.337537116},
{"learn":[9.046016712],"iteration":15,"passed_time":0.02174894616,"remaining_time":1.337560189},
{"learn":[8.983985009],"iteration":16,"passed_time":0.02319638283,"remaining_time":1.341296725},
{"learn":[8.924389528],"iteration":17,"passed_time":0.02455402649,"remaining_time":1.339558556},
{"learn":[8.871466722],"iteration":18,"passed_time":0.02590239695,"remaining_time":1.337381653},
{"learn":[8.817612205],"iteration":19,"passed_time":0.02724201118,"remaining_time":1.334858548},
{"learn":[8.768015435],"iteration":20,"passed_time":0.02859968956,"remaining_time":1.33329029},
{"learn":[8.72454377],"iteration":21,"passed_time":0.02992830063,"remaining_time":1.330449001},
{"learn":[8.678144559],"iteration":22,"passed_time":0.03125222958,"remaining_time":1.327540361},
{"learn":[8.636525629],"iteration":23,"passed_time":0.03254115752,"remaining_time":1.323340406},
{"learn":[8.597326018],"iteration":24,"passed_time":0.03382353065,"remaining_time":1.319117695},
{"learn":[8.560365954],"iteration":25,"passed_time":0.03514856454,"remaining_time":1.316719302},
{"learn":[8.523739727],"iteration":26,"passed_time":0.03661388712,"remaining_time":1.319456006},
{"learn":[8.488072796],"iteration":27,"passed_time":0.03790279038,"remaining_time":1.315768295},
{"learn":[8.457471068],"iteration":28,"passed_time":0.03914275968,"remaining_time":1.310607574},
{"learn":[8.427728562],"iteration":29,"passed_time":0.04050645277,"remaining_time":1.30970864},
{"learn":[8.399624174],"iteration":30,"passed_time":0.0418229133,"remaining_time":1.307303322},
{"learn":[8.371859757],"iteration":31,"passed_time":0.04314570335,"remaining_time":1.305157526},
{"learn":[8.347679805],"iteration":32,"passed_time":0.0444831617,"remaining_time":1.303491435},
{"learn":[8.323205263],"iteration":33,"passed_time":0.04577128331,"remaining_time":1.300442932},
{"learn":[8.300552813],"iteration":34,"passed_time":0.04706247671,"remaining_time":1.297579715},
{"learn":[8.279690634],"iteration":35,"passed_time":0.04844999942,"remaining_time":1.297383318},
{"learn":[8.257444019],"iteration":36,"passed_time":0.04940231875,"remaining_time":1.285795485},
{"learn":[8.239059101],"iteration":37,"passed_time":0.05070490882,"remaining_time":1.283634797},
{"learn":[8.219078643],"iteration":38,"passed_time":0.0520219087,"remaining_time":1.281873186},
{"learn":[8.202641439],"iteration":39,"passed_time":0.05341713517,"remaining_time":1.282011244},
{"learn":[8.188070402],"iteration":40,"passed_time":0.05481451057,"remaining_time":1.282124772},
{"learn":[8.170220241],"iteration":41,"passed_time":0.05608293221,"remaining_time":1.279224978},
{"learn":[8.154362272],"iteration":42,"passed_time":0.05733574882,"remaining_time":1.276053759},
{"learn":[8.13953483],"iteration":43,"passed_time":0.05869301053,"remaining_time":1.275239047},
{"learn":[8.127012935],"iteration":44,"passed_time":0.0601060118,"remaining_time":1.275583139},
{"learn":[8.114677755],"iteration":45,"passed_time":0.0615134081,"remaining_time":1.275734594},
{"learn":[8.101347548],"iteration":46,"passed_time":0.06302186908,"remaining_time":1.277868962},
{"learn":[8.089706368],"iteration":47,"passed_time":0.06431759607,"remaining_time":1.275632322},
{"learn":[8.080221597],"iteration":48,"passed_time":0.06579894538,"remaining_time":1.277036675},
{"learn":[8.0684982],"iteration":49,"passed_time":0.06723449,"remaining_time":1.27745531},
{"learn":[8.0598946],"iteration":50,"passed_time":0.0686663579,"remaining_time":1.277732817},
{"learn":[8.051799969],"iteration":51,"passed_time":0.07003657726,"remaining_time":1.276820678},
{"learn":[8.043687042],"iteration":52,"passed_time":0.07146648913,"remaining_time":1.276957834},
{"learn":[8.035956548],"iteration":53,"passed_time":0.07282705719,"remaining_time":1.27582215},
{"learn":[8.026312507],"iteration":54,"passed_time":0.07433675738,"remaining_time":1.27724065},
{"learn":[8.018938037],"iteration":55,"passed_time":0.07586841141,"remaining_time":1.278924649},
{"learn":[8.012850633],"iteration":56,"passed_time":0.07743361426,"remaining_time":1.281050846},
{"learn":[8.004580096],"iteration":57,"passed_time":0.07884061935,"remaining_time":1.280480404},
{"learn":[7.998632182],"iteration":58,"passed_time":0.08023672776,"remaining_time":1.279707811},
{"learn":[7.987027653],"iteration":59,"passed_time":0.08164525292,"remaining_time":1.279108962},
{"learn":[7.981359192],"iteration":60,"passed_time":0.08305592547,"remaining_time":1.278516623},
{"learn":[7.976393669],"iteration":61,"passed_time":0.0843856222,"remaining_time":1.2766728},
{"learn":[7.971966583],"iteration":62,"passed_time":0.08582043225,"remaining_time":1.276408651},
{"learn":[7.9674941],"iteration":63,"passed_time":0.08730034058,"remaining_time":1.276767481},
{"learn":[7.96251758],"iteration":64,"passed_time":0.08873117221,"remaining_time":1.276363785},
{"learn":[7.955269083],"iteration":65,"passed_time":0.09023121184,"remaining_time":1.276908361},
{"learn":[7.950788983],"iteration":66,"passed_time":0.09163988977,"remaining_time":1.276119659},
{"learn":[7.947226416],"iteration":67,"passed_time":0.09300176649,"remaining_time":1.27467127},
{"learn":[7.942142815],"iteration":68,"passed_time":0.09438577683,"remaining_time":1.273524032},
{"learn":[7.938706334],"iteration":69,"passed_time":0.09574156786,"remaining_time":1.271995116},
{"learn":[7.935605214],"iteration":70,"passed_time":0.09716111315,"remaining_time":1.271305269},
{"learn":[7.932445928],"iteration":71,"passed_time":0.0985545734,"remaining_time":1.270258946},
{"learn":[7.929696161],"iteration":72,"passed_time":0.09993395023,"remaining_time":1.269024272},
{"learn":[7.926192555],"iteration":73,"passed_time":0.1014921592,"remaining_time":1.270023506},
{"learn":[7.923376765],"iteration":74,"passed_time":0.1029004814,"remaining_time":1.269105938},
{"learn":[7.919022925],"iteration":75,"passed_time":0.1043698195,"remaining_time":1.268917279},
{"learn":[7.916169936],"iteration":76,"passed_time":0.1058574539,"remaining_time":1.268914675},
{"learn":[7.913455528],"iteration":77,"passed_time":0.1067060187,"remaining_time":1.261319863},
{"learn":[7.91015313],"iteration":78,"passed_time":0.1081705882,"remaining_time":1.261077364},
{"learn":[7.908730494],"iteration":79,"passed_time":0.1087866007,"remaining_time":1.251045907},
{"learn":[7.906043494],"iteration":80,"passed_time":0.1102093906,"remaining_time":1.250400369},
{"learn":[7.903444257],"iteration":81,"passed_time":0.111520037,"remaining_time":1.248480414},
{"learn":[7.899717775],"iteration":82,"passed_time":0.1128996484,"remaining_time":1.247337079},
{"learn":[7.895160019],"iteration":83,"passed_time":0.1143862998,"remaining_time":1.247355365},
{"learn":[7.891968149],"iteration":84,"passed_time":0.1157716713,"remaining_time":1.246247991},
{"learn":[7.884107706],"iteration":85,"passed_time":0.1171389964,"remaining_time":1.244942357},
{"learn":[7.881717567],"iteration":86,"passed_time":0.1185408232,"remaining_time":1.243997374},
{"learn":[7.879022587],"iteration":87,"passed_time":0.1199079283,"remaining_time":1.242682166},
{"learn":[7.877172356],"iteration":88,"passed_time":0.120926441,"remaining_time":1.237797615},
{"learn":[7.87517804],"iteration":89,"passed_time":0.122253292,"remaining_time":1.236116619},
{"learn":[7.873925245],"iteration":90,"passed_time":0.1236193369,"remaining_time":1.234834915},
{"learn":[7.870773572],"iteration":91,"passed_time":0.1249691781,"remaining_time":1.233391453},
{"learn":[7.864047565],"iteration":92,"passed_time":0.1262999898,"remaining_time":1.231764416},
{"learn":[7.861524601],"iteration":93,"passed_time":0.1276283748,"remaining_time":1.230120293},
{"learn":[7.860294681],"iteration":94,"passed_time":0.1289894984,"remaining_time":1.228794695},
{"learn":[7.857250916],"iteration":95,"passed_time":0.1302957235,"remaining_time":1.226951397},
{"learn":[7.854444781],"iteration":96,"passed_time":0.1316384782,"remaining_time":1.225459235},
{"learn":[7.850803353],"iteration":97,"passed_time":0.1329732737,"remaining_time":1.223896866},
{"learn":[7.845900811],"iteration":98,"passed_time":0.1343097552,"remaining_time":1.222354439},
{"learn":[7.84403468],"iteration":99,"passed_time":0.1356909561,"remaining_time":1.221218605},
{"learn":[7.842051547],"iteration":100,"passed_time":0.1372236619,"remaining_time":1.221426456},
{"learn":[7.839202535],"iteration":101,"passed_time":0.1387095208,"remaining_time":1.221187742},
{"learn":[7.836614173],"iteration":102,"passed_time":0.140082035,"remaining_time":1.219937722},
{"learn":[7.834231771],"iteration":103,"passed_time":0.1415140387,"remaining_time":1.219197872},
{"learn":[7.831475839],"iteration":104,"passed_time":0.1429016015,"remaining_time":1.218066032},
{"learn":[7.828848938],"iteration":105,"passed_time":0.1442488203,"remaining_time":1.216589107},
{"learn":[7.827481766],"iteration":106,"passed_time":0.1456172928,"remaining_time":1.215291986},
{"learn":[7.826381199],"iteration":107,"passed_time":0.1464614718,"remaining_time":1.209663267},
{"learn":[7.823094355],"iteration":108,"passed_time":0.1478372147,"remaining_time":1.208467507},
{"learn":[7.821594048],"iteration":109,"passed_time":0.1492263292,"remaining_time":1.207376664},
{"learn":[7.819212722],"iteration":110,"passed_time":0.150564185,"remaining_time":1.205869914},
{"learn":[7.817518499],"iteration":111,"passed_time":0.1520287406,"remaining_time":1.205370729},
{"learn":[7.816754429],"iteration":112,"passed_time":0.1533651904,"remaining_time":1.203848884},
{"learn":[7.809590593],"iteration":113,"passed_time":0.1546591547,"remaining_time":1.202000097},
{"learn":[7.808706241],"iteration":114,"passed_time":0.1560957518,"remaining_time":1.201258611},
{"learn":[7.808168807],"iteration":115,"passed_time":0.1574751656,"remaining_time":1.200069366},
{"learn":[7.806770327],"iteration":116,"passed_time":0.1588556783,"remaining_time":1.198885162},
{"learn":[7.806088851],"iteration":117,"passed_time":0.1601840825,"remaining_time":1.197308142},
{"learn":[7.804529879],"iteration":118,"passed_time":0.1620152894,"remaining_time":1.199457731},
{"learn":[7.801920895],"iteration":119,"passed_time":0.16358225,"remaining_time":1.199603167},
{"learn":[7.798094029],"iteration":120,"passed_time":0.1649603043,"remaining_time":1.198347995},
{"learn":[7.796449405],"iteration":121,"passed_time":0.1663911251,"remaining_time":1.197470556},
{"learn":[7.794568554],"iteration":122,"passed_time":0.1678989958,"remaining_time":1.19713349},
{"learn":[7.793632814],"iteration":123,"passed_time":0.169373303,"remaining_time":1.196540431},
{"learn":[7.793140838],"iteration":124,"passed_time":0.1712113548,"remaining_time":1.198479484},
{"learn":[7.792571937],"iteration":125,"passed_time":0.1725452962,"remaining_time":1.196861816},
{"learn":[7.792041107],"iteration":126,"passed_time":0.1739172084,"remaining_time":1.19550963},
{"learn":[7.789951118],"iteration":127,"passed_time":0.1753376079,"remaining_time":1.194487454},
{"learn":[7.782770638],"iteration":128,"passed_time":0.1767168744,"remaining_time":1.193181377},
{"learn":[7.780496729],"iteration":129,"passed_time":0.1781051525,"remaining_time":1.191934482},
{"learn":[7.780212239],"iteration":130,"passed_time":0.1794573239,"remaining_time":1.190445912},
{"learn":[7.779426445],"iteration":131,"passed_time":0.1808227493,"remaining_time":1.189046563},
{"learn":[7.778148601],"iteration":132,"passed_time":0.1822315445,"remaining_time":1.187930444},
{"learn":[7.777228628],"iteration":133,"passed_time":0.1835896604,"remaining_time":1.186482432},
{"learn":[7.776193746],"iteration":134,"passed_time":0.1849531158,"remaining_time":1.185069964},
{"learn":[7.769402945],"iteration":135,"passed_time":0.1863521849,"remaining_time":1.183884469},
{"learn":[7.768152396],"iteration":136,"passed_time":0.187689134,"remaining_time":1.182304545},
{"learn":[7.76773546],"iteration":137,"passed_time":0.1891476085,"remaining_time":1.181487236},
{"learn":[7.766269605],"iteration":138,"passed_time":0.1906460031,"remaining_time":1.180907976},
{"learn":[7.764783224],"iteration":139,"passed_time":0.1919657545,"remaining_time":1.179218206},
{"learn":[7.762824436],"iteration":140,"passed_time":0.1933571129,"remaining_time":1.177969929},
{"learn":[7.761135997],"iteration":141,"passed_time":0.1948180474,"remaining_time":1.177140033},
{"learn":[7.756428888],"iteration":142,"passed_time":0.1962996903,"remaining_time":1.176425416},
{"learn":[7.756132268],"iteration":143,"passed_time":0.1976301578,"remaining_time":1.174801494},
{"learn":[7.753278905],"iteration":144,"passed_time":0.1990519446,"remaining_time":1.173720087},
{"learn":[7.75241205],"iteration":145,"passed_time":0.200438232,"remaining_time":1.172426371},
{"learn":[7.751652176],"iteration":146,"passed_time":0.201767465,"remaining_time":1.170800324},
{"learn":[7.749615498],"iteration":147,"passed_time":0.203162578,"remaining_time":1.169557544},
{"learn":[7.748361987],"iteration":148,"passed_time":0.2045782167,"remaining_time":1.168429949},
{"learn":[7.747605881],"iteration":149,"passed_time":0.2059284043,"remaining_time":1.166927624},
{"learn":[7.741009356],"iteration":150,"passed_time":0.2073266863,"remaining_time":1.165697726},
{"learn":[7.735180926],"iteration":151,"passed_time":0.208782299,"remaining_time":1.164785457},
{"learn":[7.733849595],"iteration":152,"passed_time":0.2101875073,"remaining_time":1.16358705},
{"learn":[7.732727644],"iteration":153,"passed_time":0.2117625463,"remaining_time":1.163318923},
{"learn":[7.731957004],"iteration":154,"passed_time":0.2132563359,"remaining_time":1.162590992},
{"learn":[7.728793185],"iteration":155,"passed_time":0.2148462009,"remaining_time":1.162373036},
{"learn":[7.727690958],"iteration":156,"passed_time":0.2163068136,"remaining_time":1.161443592},
{"learn":[7.726644644],"iteration":157,"passed_time":0.2176491439,"remaining_time":1.159877083},
{"learn":[7.725854141],"iteration":158,"passed_time":0.2190788876,"remaining_time":1.158775751},
{"learn":[7.72469001],"iteration":159,"passed_time":0.2205270426,"remaining_time":1.157766974},
{"learn":[7.723834454],"iteration":160,"passed_time":0.221898495,"remaining_time":1.156353027},
{"learn":[7.722458145],"iteration":161,"passed_time":0.2231736181,"remaining_time":1.154441308},
{"learn":[7.721711958],"iteration":162,"passed_time":0.2246573821,"remaining_time":1.153608766},
{"learn":[7.720671308],"iteration":163,"passed_time":0.2260818156,"remaining_time":1.15246584},
{"learn":[7.718787359],"iteration":164,"passed_time":0.2275061449,"remaining_time":1.151318975},
{"learn":[7.718025703],"iteration":165,"passed_time":0.229042062,"remaining_time":1.150729396},
{"learn":[7.717536854],"iteration":166,"passed_time":0.2298239744,"remaining_time":1.146367489},
{"learn":[7.716511799],"iteration":167,"passed_time":0.2313482202,"remaining_time":1.145724519},
{"learn":[7.715838732],"iteration":168,"passed_time":0.2327018978,"remaining_time":1.144232409},
{"learn":[7.714064785],"iteration":169,"passed_time":0.2340267457,"remaining_time":1.14260117},
{"learn":[7.713276912],"iteration":170,"passed_time":0.2354188865,"remaining_time":1.141299748},
{"learn":[7.712108348],"iteration":171,"passed_time":0.2367730788,"remaining_time":1.139814589},
{"learn":[7.711583157],"iteration":172,"passed_time":0.2382255768,"remaining_time":1.138800879},
{"learn":[7.711185753],"iteration":173,"passed_time":0.239757313,"remaining_time":1.138158279},
{"learn":[7.710243562],"iteration":174,"passed_time":0.2412205129,"remaining_time":1.137182418},
{"learn":[7.709222559],"iteration":175,"passed_time":0.2425915016,"remaining_time":1.135769303},
{"learn":[7.708389467],"iteration":176,"passed_time":0.2441165954,"remaining_time":1.135073209},
{"learn":[7.704328903],"iteration":177,"passed_time":0.2454844081,"remaining_time":1.13364148},
{"learn":[7.703353999],"iteration":178,"passed_time":0.2468219868,"remaining_time":1.132071794},
{"learn":[7.702667585],"iteration":179,"passed_time":0.2482096766,"remaining_time":1.130732971},
{"learn":[7.701319532],"iteration":180,"passed_time":0.2496087248,"remaining_time":1.129445003},
{"learn":[7.697522418],"iteration":181,"passed_time":0.2510484041,"remaining_time":1.128338432},
{"learn":[7.695788894],"iteration":182,"passed_time":0.252468307,"remaining_time":1.127139928},
{"learn":[7.694269944],"iteration":183,"passed_time":0.2539264938,"remaining_time":1.126108799},
{"learn":[7.692887589],"iteration":184,"passed_time":0.255309496,"remaining_time":1.124741834},
{"learn":[7.691502081],"iteration":185,"passed_time":0.256540294,"remaining_time":1.122708598},
{"learn":[7.689550186],"iteration":186,"passed_time":0.257983844,"remaining_time":1.121608905},
{"learn":[7.688722403],"iteration":187,"passed_time":0.2593724239,"remaining_time":1.120268129},
{"learn":[7.687315637],"iteration":188,"passed_time":0.26074434,"remaining_time":1.118855343},
{"learn":[7.686227124],"iteration":189,"passed_time":0.2620640513,"remaining_time":1.117220429},
{"learn":[7.685362386],"iteration":190,"passed_time":0.2634013893,"remaining_time":1.115663476},
{"learn":[7.683964916],"iteration":191,"passed_time":0.2648363351,"remaining_time":1.114519577},
{"learn":[7.680032981],"iteration":192,"passed_time":0.2661556128,"remaining_time":1.112889013},
{"learn":[7.679225976],"iteration":193,"passed_time":0.2674741027,"remaining_time":1.111258385},
{"learn":[7.678143297],"iteration":194,"passed_time":0.2688044383,"remaining_time":1.109679861},
{"learn":[7.676975997],"iteration":195,"passed_time":0.2701477567,"remaining_time":1.108157124},
{"learn":[7.670346574],"iteration":196,"passed_time":0.2714315025,"remaining_time":1.106393383},
{"learn":[7.669967379],"iteration":197,"passed_time":0.2728545632,"remaining_time":1.105198786},
{"learn":[7.668510896],"iteration":198,"passed_time":0.2741647081,"remaining_time":1.103547393},
{"learn":[7.6679787],"iteration":199,"passed_time":0.275595652,"remaining_time":1.102382608},
{"learn":[7.666982659],"iteration":200,"passed_time":0.2769573443,"remaining_time":1.100939891},
{"learn":[7.664509691],"iteration":201,"passed_time":0.278387539,"remaining_time":1.099768595},
{"learn":[7.66367188],"iteration":202,"passed_time":0.2797430395,"remaining_time":1.09830149},
{"learn":[7.658442933],"iteration":203,"passed_time":0.2810760912,"remaining_time":1.096747885},
{"learn":[7.653535607],"iteration":204,"passed_time":0.2824848085,"remaining_time":1.095489867},
{"learn":[7.652528916],"iteration":205,"passed_time":0.2837108633,"remaining_time":1.093526337},
{"learn":[7.647477384],"iteration":206,"passed_time":0.2849596822,"remaining_time":1.09165714},
{"learn":[7.645033693],"iteration":207,"passed_time":0.2863308846,"remaining_time":1.090259907},
{"learn":[7.643837673],"iteration":208,"passed_time":0.2875238737,"remaining_time":1.088188441},
{"learn":[7.639572553],"iteration":209,"passed_time":0.288869765,"remaining_time":1.086700544},
{"learn":[7.63855368],"iteration":210,"passed_time":0.2901077196,"remaining_time":1.084810383},
{"learn":[7.637649292],"iteration":211,"passed_time":0.2912907217,"remaining_time":1.082722117},
{"learn":[7.636958718],"iteration":212,"passed_time":0.2925332651,"remaining_time":1.080862346},
{"learn":[7.636060766],"iteration":213,"passed_time":0.2938053581,"remaining_time":1.079116876},
{"learn":[7.634639067],"iteration":214,"passed_time":0.2950687218,"remaining_time":1.077343938},
{"learn":[7.633749041],"iteration":215,"passed_time":0.2962671507,"remaining_time":1.075340029},
{"learn":[7.632547107],"iteration":216,"passed_time":0.2975962379,"remaining_time":1.073814997},
{"learn":[7.631665653],"iteration":217,"passed_time":0.2989323683,"remaining_time":1.072317028},
{"learn":[7.629976918],"iteration":218,"passed_time":0.3003656328,"remaining_time":1.071166937},
{"learn":[7.628909725],"iteration":219,"passed_time":0.3017046645,"remaining_time":1.069680174},
{"learn":[7.623859112],"iteration":220,"passed_time":0.3031030638,"remaining_time":1.068404012},
{"learn":[7.622333049],"iteration":221,"passed_time":0.3044021106,"remaining_time":1.066778568},
{"learn":[7.621434852],"iteration":222,"passed_time":0.3056780107,"remaining_time":1.065075401},
{"learn":[7.620282975],"iteration":223,"passed_time":0.30715249,"remaining_time":1.064063983},
{"learn":[7.619781415],"iteration":224,"passed_time":0.3085132695,"remaining_time":1.062656817},
{"learn":[7.618157529],"iteration":225,"passed_time":0.3097369455,"remaining_time":1.060780512},
{"learn":[7.616771829],"iteration":226,"passed_time":0.3110770728,"remaining_time":1.059306508},
{"learn":[7.613200015],"iteration":227,"passed_time":0.3123632816,"remaining_time":1.057651111},
{"learn":[7.612312947],"iteration":228,"passed_time":0.3137376314,"remaining_time":1.056295694},
{"learn":[7.610919356],"iteration":229,"passed_time":0.3151340384,"remaining_time":1.055013955},
{"learn":[7.608464397],"iteration":230,"passed_time":0.3163893736,"remaining_time":1.053261594},
{"learn":[7.606179348],"iteration":231,"passed_time":0.3176432095,"remaining_time":1.051508556},
{"learn":[7.604687748],"iteration":232,"passed_time":0.3189498744,"remaining_time":1.049933707},
{"learn":[7.604417898],"iteration":233,"passed_time":0.3196583018,"remaining_time":1.046402817},
{"learn":[7.602799213],"iteration":234,"passed_time":0.3210528955,"remaining_time":1.045129639},
{"learn":[7.600281903],"iteration":235,"passed_time":0.3224637988,"remaining_time":1.04390823},
{"learn":[7.599405211],"iteration":236,"passed_time":0.3237847578,"remaining_time":1.042395655},
{"learn":[7.598779343],"iteration":237,"passed_time":0.325176318,"remaining_time":1.041110732},
{"learn":[7.596512823],"iteration":238,"passed_time":0.3269858661,"remaining_time":1.041155833},
{"learn":[7.595464723],"iteration":239,"passed_time":0.3286186782,"remaining_time":1.040625814},
{"learn":[7.594942675],"iteration":240,"passed_time":0.3301484912,"remaining_time":1.039762261},
{"learn":[7.59397517],"iteration":241,"passed_time":0.3315989734,"remaining_time":1.038644718},
{"learn":[7.592756201],"iteration":242,"passed_time":0.3331494489,"remaining_time":1.037835938},
{"learn":[7.587860378],"iteration":243,"passed_time":0.3344061047,"remaining_time":1.036110718},
{"learn":[7.58673678],"iteration":244,"passed_time":0.3356796128,"remaining_time":1.034441256},
{"learn":[7.585891652],"iteration":245,"passed_time":0.3371443204,"remaining_time":1.033361047},
{"learn":[7.579527711],"iteration":246,"passed_time":0.3385230606,"remaining_time":1.032015646},
{"learn":[7.578227624],"iteration":247,"passed_time":0.3400376505,"remaining_time":1.031081908},
{"learn":[7.576925607],"iteration":248,"passed_time":0.3414920401,"remaining_time":1.029961936},
{"learn":[7.576110745],"iteration":249,"passed_time":0.3428954491,"remaining_time":1.028686347},
{"learn":[7.575274939],"iteration":250,"passed_time":0.3443053655,"remaining_time":1.027429158},
{"learn":[7.574470278],"iteration":251,"passed_time":0.3456609096,"remaining_time":1.026009367},
{"learn":[7.573233665],"iteration":252,"passed_time":0.3471288364,"remaining_time":1.0249219},
{"learn":[7.571521042],"iteration":253,"passed_time":0.3486168343,"remaining_time":1.023890387},
{"learn":[7.569280385],"iteration":254,"passed_time":0.3499322894,"remaining_time":1.022351198},
{"learn":[7.568721931],"iteration":255,"passed_time":0.3511342778,"remaining_time":1.020483995},
{"learn":[7.567983128],"iteration":256,"passed_time":0.352203293,"remaining_time":1.018237536},
{"learn":[7.566113183],"iteration":257,"passed_time":0.3536198792,"remaining_time":1.016999808},
{"learn":[7.561452017],"iteration":258,"passed_time":0.3549459741,"remaining_time":1.015501802},
{"learn":[7.560638698],"iteration":259,"passed_time":0.3562913507,"remaining_time":1.014059998},
{"learn":[7.560014975],"iteration":260,"passed_time":0.3576746558,"remaining_time":1.012726324},
{"learn":[7.559178097],"iteration":261,"passed_time":0.3590163341,"remaining_time":1.011275017},
{"learn":[7.557513647],"iteration":262,"passed_time":0.3604261717,"remaining_time":1.010015546},
{"learn":[7.555298153],"iteration":263,"passed_time":0.3617805368,"remaining_time":1.008600284},
{"learn":[7.553536765],"iteration":264,"passed_time":0.3630993315,"remaining_time":1.007086825},
{"learn":[7.55297081],"iteration":265,"passed_time":0.3643557939,"remaining_time":1.00540283},
{"learn":[7.552349697],"iteration":266,"passed_time":0.3657042469,"remaining_time":1.003974581},
{"learn":[7.550727601],"iteration":267,"passed_time":0.3670318866,"remaining_time":1.002490078},
{"learn":[7.549842996],"iteration":268,"passed_time":0.3683198639,"remaining_time":1.000898961},
{"learn":[7.549106117],"iteration":269,"passed_time":0.3697779071,"remaining_time":0.999769897},
{"learn":[7.548148657],"iteration":270,"passed_time":0.3711196942,"remaining_time":0.9983256718},
{"learn":[7.546419223],"iteration":271,"passed_time":0.3724502489,"remaining_time":0.9968521369},
{"learn":[7.54579465],"iteration":272,"passed_time":0.3737427865,"remaining_time":0.9952784094},
{"learn":[7.544772842],"iteration":273,"passed_time":0.3751070907,"remaining_time":0.9938968899},
{"learn":[7.5434947],"iteration":274,"passed_time":0.3764388503,"remaining_time":0.9924296963},
{"learn":[7.542650622],"iteration":275,"passed_time":0.3777642229,"remaining_time":0.9909467297},
{"learn":[7.540793726],"iteration":276,"passed_time":0.3790863953,"remaining_time":0.989456548},
{"learn":[7.538600299],"iteration":277,"passed_time":0.3804313383,"remaining_time":0.9880267131},
{"learn":[7.538008324],"iteration":278,"passed_time":0.3817651508,"remaining_time":0.9865687229},
{"learn":[7.53745984],"iteration":279,"passed_time":0.3830826723,"remaining_time":0.9850697287},
{"learn":[7.536788474],"iteration":280,"passed_time":0.3844164354,"remaining_time":0.9836135837},
{"learn":[7.536085649],"iteration":281,"passed_time":0.3857251698,"remaining_time":0.9820945812},
{"learn":[7.533467564],"iteration":282,"passed_time":0.3870522862,"remaining_time":0.9806236369},
{"learn":[7.532383482],"iteration":283,"passed_time":0.3884990354,"remaining_time":0.9794553146},
{"learn":[7.528109682],"iteration":284,"passed_time":0.3898717525,"remaining_time":0.9780993088},
{"learn":[7.527148804],"iteration":285,"passed_time":0.3913793793,"remaining_time":0.977079989},
{"learn":[7.526211091],"iteration":286,"passed_time":0.3927772401,"remaining_time":0.975784572},
{"learn":[7.525496999],"iteration":287,"passed_time":0.3940692421,"remaining_time":0.9742267375},
{"learn":[7.522647065],"iteration":288,"passed_time":0.3954826357,"remaining_time":0.9729693911},
{"learn":[7.521939756],"iteration":289,"passed_time":0.3968071426,"remaining_time":0.9714933492},
{"learn":[7.51937284],"iteration":290,"passed_time":0.3981314971,"remaining_time":0.9700179775},
{"learn":[7.518532885],"iteration":291,"passed_time":0.3993829264,"remaining_time":0.9683668215},
{"learn":[7.51692683],"iteration":292,"passed_time":0.400787828,"remaining_time":0.9670887182},
{"learn":[7.515420646],"iteration":293,"passed_time":0.402156836,"remaining_time":0.9657235585},
{"learn":[7.514691468],"iteration":294,"passed_time":0.4035665101,"remaining_time":0.9644555579},
{"learn":[7.513036325],"iteration":295,"passed_time":0.4049330882,"remaining_time":0.9630841017},
{"learn":[7.512395413],"iteration":296,"passed_time":0.4062585465,"remaining_time":0.9616153474},
{"learn":[7.511694221],"iteration":297,"passed_time":0.407630941,"remaining_time":0.9602581228},
{"learn":[7.510588347],"iteration":298,"passed_time":0.4089884033,"remaining_time":0.9588657884},
{"learn":[7.509746378],"iteration":299,"passed_time":0.4104199556,"remaining_time":0.9576465632},
{"learn":[7.509111245],"iteration":300,"passed_time":0.4117735792,"remaining_time":0.9562449564},
{"learn":[7.507466646],"iteration":301,"passed_time":0.4129712207,"remaining_time":0.9544831525},
{"learn":[7.505926471],"iteration":302,"passed_time":0.414362686,"remaining_time":0.9531709311},
{"learn":[7.502831881],"iteration":303,"passed_time":0.4157350311,"remaining_time":0.9518144133},
{"learn":[7.499203445],"iteration":304,"passed_time":0.4171672609,"remaining_time":0.9505942502},
{"learn":[7.49858616],"iteration":305,"passed_time":0.4183672542,"remaining_time":0.9488459949},
{"learn":[7.498230821],"iteration":306,"passed_time":0.4197302803,"remaining_time":0.9474693297},
{"learn":[7.497736727],"iteration":307,"passed_time":0.4211257552,"remaining_time":0.9461656578},
{"learn":[7.496140072],"iteration":308,"passed_time":0.4224827006,"remaining_time":0.94477523},
{"learn":[7.493871829],"iteration":309,"passed_time":0.4238592926,"remaining_time":0.9434287481},
{"learn":[7.491255427],"iteration":310,"passed_time":0.4252913967,"remaining_time":0.9422050556},
{"learn":[7.487740452],"iteration":311,"passed_time":0.426660427,"remaining_time":0.9408409415},
{"learn":[7.487418677],"iteration":312,"passed_time":0.4280109865,"remaining_time":0.9394362547},
{"learn":[7.486936038],"iteration":313,"passed_time":0.4293586949,"remaining_time":0.9380256837},
{"learn":[7.486280147],"iteration":314,"passed_time":0.4307226974,"remaining_time":0.9366509451},
{"learn":[7.485802962],"iteration":315,"passed_time":0.4320682677,"remaining_time":0.9352363769},
{"learn":[7.484316288],"iteration":316,"passed_time":0.4335034265,"remaining_time":0.9340152691},
{"learn":[7.481111316],"iteration":317,"passed_time":0.43488371,"remaining_time":0.9326751264},
{"learn":[7.477176988],"iteration":318,"passed_time":0.436201047,"remaining_time":0.9312003543},
{"learn":[7.470995277],"iteration":319,"passed_time":0.4374719417,"remaining_time":0.9296278761},
{"learn":[7.469471252],"iteration":320,"passed_time":0.4388853496,"remaining_time":0.9283587302},
{"learn":[7.468063191],"iteration":321,"passed_time":0.4402674016,"remaining_time":0.9270226655},
{"learn":[7.467563549],"iteration":322,"passed_time":0.4415977295,"remaining_time":0.9255779036},
{"learn":[7.466799914],"iteration":323,"passed_time":0.4429568793,"remaining_time":0.9241939828},
{"learn":[7.466311258],"iteration":324,"passed_time":0.4443495711,"remaining_time":0.9228798784},
{"learn":[7.464840131],"iteration":325,"passed_time":0.4456987679,"remaining_time":0.9214753668},
{"learn":[7.46406699],"iteration":326,"passed_time":0.4469964205,"remaining_time":0.91996511},
{"learn":[7.463189487],"iteration":327,"passed_time":0.4483029774,"remaining_time":0.9184743927},
{"learn":[7.462738804],"iteration":328,"passed_time":0.4497356624,"remaining_time":0.9172420349},
{"learn":[7.461312915],"iteration":329,"passed_time":0.4511082969,"remaining_time":0.9158865422},
{"learn":[7.460870118],"iteration":330,"passed_time":0.4524310445,"remaining_time":0.9144301172},
{"learn":[7.460432949],"iteration":331,"passed_time":0.4537703933,"remaining_time":0.9130078998},
{"learn":[7.46000509],"iteration":332,"passed_time":0.4550956664,"remaining_time":0.9115579865},
{"learn":[7.45946753],"iteration":333,"passed_time":0.4563971523,"remaining_time":0.9100613875},
{"learn":[7.458179509],"iteration":334,"passed_time":0.4578168697,"remaining_time":0.9088006517},
{"learn":[7.455507102],"iteration":335,"passed_time":0.4592120467,"remaining_time":0.9074904733},
{"learn":[7.453975187],"iteration":336,"passed_time":0.4605706009,"remaining_time":0.9061077401},
{"learn":[7.452598658],"iteration":337,"passed_time":0.4620012589,"remaining_time":0.904866371},
{"learn":[7.451363271],"iteration":338,"passed_time":0.4633881165,"remaining_time":0.9035384809},
{"learn":[7.450509443],"iteration":339,"passed_time":0.464771971,"remaining_time":0.9022044143},
{"learn":[7.449579499],"iteration":340,"passed_time":0.4663488992,"remaining_time":0.9012431806},
{"learn":[7.446531766],"iteration":341,"passed_time":0.467833333,"remaining_time":0.9001003893},
{"learn":[7.444733743],"iteration":342,"passed_time":0.4694104272,"remaining_time":0.8991330923},
{"learn":[7.444326205],"iteration":343,"passed_time":0.470892878,"remaining_time":0.8979817673},
{"learn":[7.443811095],"iteration":344,"passed_time":0.4723798851,"remaining_time":0.8968371732},
{"learn":[7.43995523],"iteration":345,"passed_time":0.4739400555,"remaining_time":0.8958288911},
{"learn":[7.43483238],"iteration":346,"passed_time":0.4753945871,"remaining_time":0.8946186323},
{"learn":[7.433508874],"iteration":347,"passed_time":0.4768886954,"remaining_time":0.893481119},
{"learn":[7.43231838],"iteration":348,"passed_time":0.4783245178,"remaining_time":0.8922328398},
{"learn":[7.431005633],"iteration":349,"passed_time":0.479778372,"remaining_time":0.8910169765},
{"learn":[7.430324716],"iteration":350,"passed_time":0.481209611,"remaining_time":0.8897579417},
{"learn":[7.429110952],"iteration":351,"passed_time":0.4826638548,"remaining_time":0.8885402782},
{"learn":[7.426417273],"iteration":352,"passed_time":0.4841868298,"remaining_time":0.8874472489},
{"learn":[7.425865998],"iteration":353,"passed_time":0.4856560089,"remaining_time":0.8862536207},
{"learn":[7.423126578],"iteration":354,"passed_time":0.4871463015,"remaining_time":0.8850968014},
{"learn":[7.422670114],"iteration":355,"passed_time":0.4884522797,"remaining_time":0.8836046858},
{"learn":[7.421454787],"iteration":356,"passed_time":0.4899067041,"remaining_time":0.8823809825},
{"learn":[7.420720909],"iteration":357,"passed_time":0.4912338707,"remaining_time":0.8809277793},
{"learn":[7.419449022],"iteration":358,"passed_time":0.4926267037,"remaining_time":0.8795925266},
{"learn":[7.418789631],"iteration":359,"passed_time":0.4941021899,"remaining_time":0.8784038931},
{"learn":[7.418147407],"iteration":360,"passed_time":0.4955859524,"remaining_time":0.8772283202},
{"learn":[7.414921953],"iteration":361,"passed_time":0.497069502,"remaining_time":0.8760506692},
{"learn":[7.41367076],"iteration":362,"passed_time":0.4984921684,"remaining_time":0.8747644939},
{"learn":[7.412664208],"iteration":363,"passed_time":0.49985586,"remaining_time":0.8733745245},
{"learn":[7.412164978],"iteration":364,"passed_time":0.501193343,"remaining_time":0.8719391036},
{"learn":[7.411019358],"iteration":365,"passed_time":0.5025718587,"remaining_time":0.8705752962},
{"learn":[7.40979387],"iteration":366,"passed_time":0.5039678923,"remaining_time":0.8692416235},
{"learn":[7.408662316],"iteration":367,"passed_time":0.5053130451,"remaining_time":0.8678202297},
{"learn":[7.405428999],"iteration":368,"passed_time":0.5066715892,"remaining_time":0.8664221486},
{"learn":[7.402524797],"iteration":369,"passed_time":0.508003671,"remaining_time":0.8649792236},
{"learn":[7.400124646],"iteration":370,"passed_time":0.5094636494,"remaining_time":0.8637537345},
{"learn":[7.399216999],"iteration":371,"passed_time":0.5109372236,"remaining_time":0.8625499367},
{"learn":[7.396084409],"iteration":372,"passed_time":0.5123521964,"remaining_time":0.8612461853},
{"learn":[7.395224037],"iteration":373,"passed_time":0.5137131109,"remaining_time":0.8598513567},
{"learn":[7.39436466],"iteration":374,"passed_time":0.5150989893,"remaining_time":0.8584983155},
{"learn":[7.391346975],"iteration":375,"passed_time":0.5165151966,"remaining_time":0.8571954326},
{"learn":[7.390188542],"iteration":376,"passed_time":0.5179514426,"remaining_time":0.855925063},
{"learn":[7.389811317],"iteration":377,"passed_time":0.5193028956,"remaining_time":0.8545142886},
{"learn":[7.389159245],"iteration":378,"passed_time":0.5206257683,"remaining_time":0.8530569976},
{"learn":[7.38886581],"iteration":379,"passed_time":0.5219538569,"remaining_time":0.8516089245},
{"learn":[7.387750312],"iteration":380,"passed_time":0.5232733476,"remaining_time":0.8501475122},
{"learn":[7.387113874],"iteration":381,"passed_time":0.5246411271,"remaining_time":0.8487649648},
{"learn":[7.385800749],"iteration":382,"passed_time":0.5260516978,"remaining_time":0.8474514296},
{"learn":[7.385241382],"iteration":383,"passed_time":0.5274750394,"remaining_time":0.8461578757},
{"learn":[7.384149312],"iteration":384,"passed_time":0.5288727497,"remaining_time":0.8448227041},
{"learn":[7.383722109],"iteration":385,"passed_time":0.5301682255,"remaining_time":0.8433245867},
{"learn":[7.381176123],"iteration":386,"passed_time":0.5314748403,"remaining_time":0.8418451605},
{"learn":[7.379149209],"iteration":387,"passed_time":0.532883161,"remaining_time":0.8405270478},
{"learn":[7.378784104],"iteration":388,"passed_time":0.5342714453,"remaining_time":0.8391770002},
{"learn":[7.378499982],"iteration":389,"passed_time":0.5356722644,"remaining_time":0.8378463622},
{"learn":[7.377956363],"iteration":390,"passed_time":0.5371053306,"remaining_time":0.8365655916},
{"learn":[7.376962633],"iteration":391,"passed_time":0.5384740993,"remaining_time":0.8351843173},
{"learn":[7.375093067],"iteration":392,"passed_time":0.539800134,"remaining_time":0.8337371026},
{"learn":[7.374321741],"iteration":393,"passed_time":0.5411097573,"remaining_time":0.8322652612},
{"learn":[7.374041316],"iteration":394,"passed_time":0.5425519154,"remaining_time":0.8309972375},
{"learn":[7.373545235],"iteration":395,"passed_time":0.5439566612,"remaining_time":0.8296712711},
{"learn":[7.373193313],"iteration":396,"passed_time":0.5453103843,"remaining_time":0.8282674099},
{"learn":[7.3711023],"iteration":397,"passed_time":0.546791072,"remaining_time":0.8270558425},
{"learn":[7.370729001],"iteration":398,"passed_time":0.5481341723,"remaining_time":0.8256356831},
{"learn":[7.370388511],"iteration":399,"passed_time":0.5495133686,"remaining_time":0.8242700529},
{"learn":[7.369108033],"iteration":400,"passed_time":0.5508787029,"remaining_time":0.8228836485},
{"learn":[7.36754419],"iteration":401,"passed_time":0.5523031093,"remaining_time":0.8215852223},
{"learn":[7.365793155],"iteration":402,"passed_time":0.5535998637,"remaining_time":0.8200970686},
{"learn":[7.365281646],"iteration":403,"passed_time":0.5549937962,"remaining_time":0.8187532241},
{"learn":[7.364558464],"iteration":404,"passed_time":0.5564244284,"remaining_time":0.8174630491},
{"learn":[7.364179032],"iteration":405,"passed_time":0.5578528738,"remaining_time":0.8161689828},
{"learn":[7.363739466],"iteration":406,"passed_time":0.559241949,"remaining_time":0.8148168937},
{"learn":[7.362200085],"iteration":407,"passed_time":0.5606717343,"remaining_time":0.8135236929},
{"learn":[7.361148069],"iteration":408,"passed_time":0.5620980798,"remaining_time":0.8122248537},
{"learn":[7.358744309],"iteration":409,"passed_time":0.563626588,"remaining_time":0.8110724071},
{"learn":[7.35779837],"iteration":410,"passed_time":0.5649665849,"remaining_time":0.8096479769},
{"learn":[7.357315602],"iteration":411,"passed_time":0.5663173782,"remaining_time":0.808239365},
{"learn":[7.356990102],"iteration":412,"passed_time":0.5676981702,"remaining_time":0.8068736704},
{"learn":[7.356734417],"iteration":413,"passed_time":0.5690297311,"remaining_time":0.8054382184},
{"learn":[7.353687869],"iteration":414,"passed_time":0.5704524778,"remaining_time":0.8041318061},
{"learn":[7.352204638],"iteration":415,"passed_time":0.5718261679,"remaining_time":0.8027559664},
{"learn":[7.351701759],"iteration":416,"passed_time":0.5732230217,"remaining_time":0.8014125219},
{"learn":[7.351398974],"iteration":417,"passed_time":0.5746001593,"remaining_time":0.8000413701},
{"learn":[7.351148788],"iteration":418,"passed_time":0.5759542566,"remaining_time":0.7986382413},
{"learn":[7.350706089],"iteration":419,"passed_time":0.5772652264,"remaining_time":0.7971757888},
{"learn":[7.3500622],"iteration":420,"passed_time":0.5786527429,"remaining_time":0.7958193305},
{"learn":[7.349530101],"iteration":421,"passed_time":0.5799862514,"remaining_time":0.7943887519},
{"learn":[7.347706061],"iteration":422,"passed_time":0.5814097658,"remaining_time":0.7930814064},
{"learn":[7.346854299],"iteration":423,"passed_time":0.5828213605,"remaining_time":0.7917573199},
{"learn":[7.346544179],"iteration":424,"passed_time":0.58412352,"remaining_time":0.7902847623},
{"learn":[7.344552988],"iteration":425,"passed_time":0.5855492173,"remaining_time":0.7889794618},
{"learn":[7.342291079],"iteration":426,"passed_time":0.5869166489,"remaining_time":0.7875954094},
{"learn":[7.338927598],"iteration":427,"passed_time":0.5882951082,"remaining_time":0.7862261727},
{"learn":[7.336156333],"iteration":428,"passed_time":0.5897097553,"remaining_time":0.784905059},
{"learn":[7.335592489],"iteration":429,"passed_time":0.5909605334,"remaining_time":0.7833662884},
{"learn":[7.335352173],"iteration":430,"passed_time":0.5922137373,"remaining_time":0.7818320569},
{"learn":[7.333637088],"iteration":431,"passed_time":0.5935624519,"remaining_time":0.7804247053},
{"learn":[7.333335684],"iteration":432,"passed_time":0.5949993669,"remaining_time":0.7791331202},
{"learn":[7.333098608],"iteration":433,"passed_time":0.5963695469,"remaining_time":0.7777538331},
{"learn":[7.332803124],"iteration":434,"passed_time":0.5977864576,"remaining_time":0.7764352839},
{"learn":[7.332279661],"iteration":435,"passed_time":0.5992950424,"remaining_time":0.7752348713},
{"learn":[7.33061634],"iteration":436,"passed_time":0.6007459968,"remaining_time":0.7739588014},
{"learn":[7.330013802],"iteration":437,"passed_time":0.6021672898,"remaining_time":0.7726438741},
{"learn":[7.328546096],"iteration":438,"passed_time":0.6035603642,"remaining_time":0.7712924017},
{"learn":[7.327438391],"iteration":439,"passed_time":0.6050012854,"remaining_time":0.770001636},
{"learn":[7.32721013],"iteration":440,"passed_time":0.6063742903,"remaining_time":0.7686241004},
{"learn":[7.326931461],"iteration":441,"passed_time":0.6077570128,"remaining_time":0.7672588533},
{"learn":[7.326385269],"iteration":442,"passed_time":0.6090726887,"remaining_time":0.765809227},
{"learn":[7.326059344],"iteration":443,"passed_time":0.6104613124,"remaining_time":0.7644515534},
{"learn":[7.325052527],"iteration":444,"passed_time":0.6118327363,"remaining_time":0.7630722891},
{"learn":[7.324851605],"iteration":445,"passed_time":0.6131540067,"remaining_time":0.7616307616},
{"learn":[7.324578316],"iteration":446,"passed_time":0.6144813523,"remaining_time":0.7601972882},
{"learn":[7.324268344],"iteration":447,"passed_time":0.6162417767,"remaining_time":0.7592979034},
{"learn":[7.323905556],"iteration":448,"passed_time":0.6176851346,"remaining_time":0.7580055884},
{"learn":[7.322408777],"iteration":449,"passed_time":0.6191301916,"remaining_time":0.7567146787},
{"learn":[7.322155389],"iteration":450,"passed_time":0.6205719115,"remaining_time":0.755419023},
{"learn":[7.319914356],"iteration":451,"passed_time":0.6219629805,"remaining_time":0.7540613126},
{"learn":[7.31965969],"iteration":452,"passed_time":0.6233069412,"remaining_time":0.7526465714},
{"learn":[7.317525003],"iteration":453,"passed_time":0.6247455769,"remaining_time":0.7513460022},
{"learn":[7.316363642],"iteration":454,"passed_time":0.626194904,"remaining_time":0.7500576323},
{"learn":[7.31450497],"iteration":455,"passed_time":0.6276281145,"remaining_time":0.7487493296},
{"learn":[7.314303069],"iteration":456,"passed_time":0.6289751277,"remaining_time":0.747338062},
{"learn":[7.313860352],"iteration":457,"passed_time":0.6304065338,"remaining_time":0.7460269461},
{"learn":[7.312914693],"iteration":458,"passed_time":0.6317888084,"remaining_time":0.7446573973},
{"learn":[7.311086855],"iteration":459,"passed_time":0.6332553085,"remaining_time":0.7433866665},
{"learn":[7.309837337],"iteration":460,"passed_time":0.6347036008,"remaining_time":0.742093798},
{"learn":[7.306073818],"iteration":461,"passed_time":0.6360052604,"remaining_time":0.7406295023},
{"learn":[7.305035961],"iteration":462,"passed_time":0.6373900516,"remaining_time":0.7392623276},
{"learn":[7.302223008],"iteration":463,"passed_time":0.6388934786,"remaining_time":0.7380321218},
{"learn":[7.300625551],"iteration":464,"passed_time":0.6403745088,"remaining_time":0.7367749725},
{"learn":[7.299233334],"iteration":465,"passed_time":0.6418728193,"remaining_time":0.7355366641},
{"learn":[7.298450316],"iteration":466,"passed_time":0.6432614496,"remaining_time":0.7341720614},
{"learn":[7.296278687],"iteration":467,"passed_time":0.6447437426,"remaining_time":0.7329138271},
{"learn":[7.29571814],"iteration":468,"passed_time":0.6461172081,"remaining_time":0.7315314233},
{"learn":[7.295134331],"iteration":469,"passed_time":0.6475572034,"remaining_time":0.7302240804},
{"learn":[7.294503354],"iteration":470,"passed_time":0.6488320927,"remaining_time":0.7287307368},
{"learn":[7.293613008],"iteration":471,"passed_time":0.6501485605,"remaining_time":0.7272848304},
{"learn":[7.291233622],"iteration":472,"passed_time":0.6515701819,"remaining_time":0.7259566297},
{"learn":[7.290990277],"iteration":473,"passed_time":0.652908857,"remaining_time":0.724535989},
{"learn":[7.290757196],"iteration":474,"passed_time":0.6541681282,"remaining_time":0.7230279311},
{"learn":[7.288934457],"iteration":475,"passed_time":0.6555802583,"remaining_time":0.7216891919},
{"learn":[7.28870342],"iteration":476,"passed_time":0.6568922805,"remaining_time":0.720240383},
{"learn":[7.286626991],"iteration":477,"passed_time":0.6583407697,"remaining_time":0.7189411752},
{"learn":[7.285690767],"iteration":478,"passed_time":0.6597636853,"remaining_time":0.7176135283},
{"learn":[7.285366468],"iteration":479,"passed_time":0.6611348322,"remaining_time":0.7162294015},
{"learn":[7.285137799],"iteration":480,"passed_time":0.662495759,"remaining_time":0.7148343013},
{"learn":[7.284619289],"iteration":481,"passed_time":0.6637993854,"remaining_time":0.7133777627},
{"learn":[7.282813378],"iteration":482,"passed_time":0.665326534,"remaining_time":0.712161114},
{"learn":[7.280907134],"iteration":483,"passed_time":0.6666596459,"remaining_time":0.7107363167},
{"learn":[7.280017255],"iteration":484,"passed_time":0.6680355728,"remaining_time":0.7093573608},
{"learn":[7.279628973],"iteration":485,"passed_time":0.6693923114,"remaining_time":0.7079581236},
{"learn":[7.277514783],"iteration":486,"passed_time":0.670793345,"remaining_time":0.7066057207},
{"learn":[7.276925435],"iteration":487,"passed_time":0.6722355339,"remaining_time":0.7052962979},
{"learn":[7.275900127],"iteration":488,"passed_time":0.6736836666,"remaining_time":0.7039925432},
{"learn":[7.275530638],"iteration":489,"passed_time":0.6750223433,"remaining_time":0.7025742757},
{"learn":[7.273513729],"iteration":490,"passed_time":0.6763393355,"remaining_time":0.7011338529},
{"learn":[7.272655106],"iteration":491,"passed_time":0.6776598778,"remaining_time":0.6996975974},
{"learn":[7.272187797],"iteration":492,"passed_time":0.6789744896,"remaining_time":0.6982557124},
{"learn":[7.271855129],"iteration":493,"passed_time":0.6803177674,"remaining_time":0.6968437051},
{"learn":[7.269898981],"iteration":494,"passed_time":0.6817254176,"remaining_time":0.6954976482},
{"learn":[7.26931958],"iteration":495,"passed_time":0.6830431127,"remaining_time":0.6940599371},
{"learn":[7.266171941],"iteration":496,"passed_time":0.6842744608,"remaining_time":0.6925353195},
{"learn":[7.265934312],"iteration":497,"passed_time":0.685683898,"remaining_time":0.6911913992},
{"learn":[7.265183688],"iteration":498,"passed_time":0.6869045022,"remaining_time":0.6896576265},
{"learn":[7.264932939],"iteration":499,"passed_time":0.6882127937,"remaining_time":0.6882127937},
{"learn":[7.263286368],"iteration":500,"passed_time":0.6896585135,"remaining_time":0.6869053857},
{"learn":[7.262974669],"iteration":501,"passed_time":0.6910256372,"remaining_time":0.6855194568},
{"learn":[7.261985315],"iteration":502,"passed_time":0.6925263551,"remaining_time":0.6842656033},
{"learn":[7.261548506],"iteration":503,"passed_time":0.693881653,"remaining_time":0.6828676586},
{"learn":[7.261184214],"iteration":504,"passed_time":0.6954065624,"remaining_time":0.6816361355},
{"learn":[7.260826982],"iteration":505,"passed_time":0.6968679899,"remaining_time":0.6803414763},
{"learn":[7.258209183],"iteration":506,"passed_time":0.698620677,"remaining_time":0.6793293763},
{"learn":[7.257939736],"iteration":507,"passed_time":0.7000590619,"remaining_time":0.6780099576},
{"learn":[7.257436829],"iteration":508,"passed_time":0.7015333205,"remaining_time":0.6767246766},
{"learn":[7.257027838],"iteration":509,"passed_time":0.7030175993,"remaining_time":0.6754482816},
{"learn":[7.255095848],"iteration":510,"passed_time":0.704559427,"remaining_time":0.6742261444},
{"learn":[7.25481272],"iteration":511,"passed_time":0.7059402567,"remaining_time":0.6728493072},
{"learn":[7.254621898],"iteration":512,"passed_time":0.7073750351,"remaining_time":0.6715236688},
{"learn":[7.252856281],"iteration":513,"passed_time":0.708894034,"remaining_time":0.6702772384},
{"learn":[7.25213555],"iteration":514,"passed_time":0.7101415867,"remaining_time":0.6687741156},
{"learn":[7.251446572],"iteration":515,"passed_time":0.7116486665,"remaining_time":0.6675154158},
{"learn":[7.251239014],"iteration":516,"passed_time":0.7133154903,"remaining_time":0.6664049939},
{"learn":[7.249395673],"iteration":517,"passed_time":0.7148215802,"remaining_time":0.6651428603},
{"learn":[7.249183108],"iteration":518,"passed_time":0.7161772261,"remaining_time":0.6637403579},
{"learn":[7.24660554],"iteration":519,"passed_time":0.7174089732,"remaining_time":0.6622236675},
{"learn":[7.244495054],"iteration":520,"passed_time":0.7186587759,"remaining_time":0.6607246711},
{"learn":[7.244147432],"iteration":521,"passed_time":0.7199558204,"remaining_time":0.6592698892},
{"learn":[7.242726499],"iteration":522,"passed_time":0.7214224616,"remaining_time":0.6579703905},
{"learn":[7.240260968],"iteration":523,"passed_time":0.7227866231,"remaining_time":0.6565771614},
{"learn":[7.23955884],"iteration":524,"passed_time":0.7241629389,"remaining_time":0.65519504},
{"learn":[7.236889763],"iteration":525,"passed_time":0.7254667131,"remaining_time":0.6537475703},
{"learn":[7.23668045],"iteration":526,"passed_time":0.7271706348,"remaining_time":0.6526597917},
{"learn":[7.236541342],"iteration":527,"passed_time":0.7286134954,"remaining_time":0.6513363065},
{"learn":[7.236315289],"iteration":528,"passed_time":0.7299339139,"remaining_time":0.6499033525},
{"learn":[7.23498699],"iteration":529,"passed_time":0.7312209684,"remaining_time":0.6484412361},
{"learn":[7.232838447],"iteration":530,"passed_time":0.7324464916,"remaining_time":0.6469254323},
{"learn":[7.23200424],"iteration":531,"passed_time":0.7339192842,"remaining_time":0.6456282425},
{"learn":[7.231530011],"iteration":532,"passed_time":0.7352982381,"remaining_time":0.6442481749},
{"learn":[7.229140153],"iteration":533,"passed_time":0.7366535191,"remaining_time":0.642847453},
{"learn":[7.228889865],"iteration":534,"passed_time":0.7378730022,"remaining_time":0.6413288711},
{"learn":[7.22601467],"iteration":535,"passed_time":0.7392299499,"remaining_time":0.6399304044},
{"learn":[7.224613573],"iteration":536,"passed_time":0.7404458064,"remaining_time":0.6384104439},
{"learn":[7.224434233],"iteration":537,"passed_time":0.7419926557,"remaining_time":0.6371758493},
{"learn":[7.221859218],"iteration":538,"passed_time":0.7433878382,"remaining_time":0.6358103774},
{"learn":[7.221681456],"iteration":539,"passed_time":0.7447153891,"remaining_time":0.6343871833},
{"learn":[7.221412048],"iteration":540,"passed_time":0.746096833,"remaining_time":0.6330100672},
{"learn":[7.221163565],"iteration":541,"passed_time":0.7473772694,"remaining_time":0.6315475819},
{"learn":[7.220660394],"iteration":542,"passed_time":0.7487055117,"remaining_time":0.6301260015},
{"learn":[7.220283344],"iteration":543,"passed_time":0.7499460111,"remaining_time":0.6286312152},
{"learn":[7.219020093],"iteration":544,"passed_time":0.7513200105,"remaining_time":0.6272488161},
{"learn":[7.21872897],"iteration":545,"passed_time":0.7526685754,"remaining_time":0.625845299},
{"learn":[7.218408442],"iteration":546,"passed_time":0.7540389499,"remaining_time":0.6244600444},
{"learn":[7.216555975],"iteration":547,"passed_time":0.7555002478,"remaining_time":0.6231498394},
{"learn":[7.214391589],"iteration":548,"passed_time":0.7569217838,"remaining_time":0.6218064199},
{"learn":[7.212256817],"iteration":549,"passed_time":0.7582980919,"remaining_time":0.6204257116},
{"learn":[7.209773697],"iteration":550,"passed_time":0.7596224569,"remaining_time":0.6190026917},
{"learn":[7.207907302],"iteration":551,"passed_time":0.761010255,"remaining_time":0.6176315113},
{"learn":[7.206370306],"iteration":552,"passed_time":0.7623825045,"remaining_time":0.6162477025},
{"learn":[7.206033765],"iteration":553,"passed_time":0.7637814162,"remaining_time":0.6148854},
{"learn":[7.205539396],"iteration":554,"passed_time":0.7651387535,"remaining_time":0.6134896312},
{"learn":[7.205319922],"iteration":555,"passed_time":0.7665435811,"remaining_time":0.6121319245},
{"learn":[7.204995668],"iteration":556,"passed_time":0.7678617932,"remaining_time":0.6107051605},
{"learn":[7.20460853],"iteration":557,"passed_time":0.7692725537,"remaining_time":0.6093520945},
{"learn":[7.204177397],"iteration":558,"passed_time":0.7707085088,"remaining_time":0.6080186984},
{"learn":[7.203903598],"iteration":559,"passed_time":0.772018021,"remaining_time":0.6065855879},
{"learn":[7.203365406],"iteration":560,"passed_time":0.7733700196,"remaining_time":0.605186165},
{"learn":[7.203173919],"iteration":561,"passed_time":0.7750721461,"remaining_time":0.6040597865},
{"learn":[7.200942125],"iteration":562,"passed_time":0.7764848156,"remaining_time":0.6027066864},
{"learn":[7.200371787],"iteration":563,"passed_time":0.7777986631,"remaining_time":0.6012769807},
{"learn":[7.20024271],"iteration":564,"passed_time":0.7791218555,"remaining_time":0.5998548799},
{"learn":[7.200008221],"iteration":565,"passed_time":0.7809012858,"remaining_time":0.5987829647},
{"learn":[7.199807057],"iteration":566,"passed_time":0.782487363,"remaining_time":0.5975608963},
{"learn":[7.198369312],"iteration":567,"passed_time":0.7839451007,"remaining_time":0.5962399357},
{"learn":[7.198246629],"iteration":568,"passed_time":0.7854549537,"remaining_time":0.5949579702},
{"learn":[7.197960875],"iteration":569,"passed_time":0.7868472195,"remaining_time":0.5935864989},
{"learn":[7.195967835],"iteration":570,"passed_time":0.7882468719,"remaining_time":0.5922205044},
{"learn":[7.195537406],"iteration":571,"passed_time":0.7897114445,"remaining_time":0.5909029689},
{"learn":[7.193937534],"iteration":572,"passed_time":0.7911616605,"remaining_time":0.5895742217},
{"learn":[7.192708657],"iteration":573,"passed_time":0.7925995253,"remaining_time":0.5882358846},
{"learn":[7.192336845],"iteration":574,"passed_time":0.7939263864,"remaining_time":0.5868151552},
{"learn":[7.192115738],"iteration":575,"passed_time":0.795297828,"remaining_time":0.5854275678},
{"learn":[7.191889741],"iteration":576,"passed_time":0.7966073101,"remaining_time":0.5839946138},
{"learn":[7.191424499],"iteration":577,"passed_time":0.7979720749,"remaining_time":0.5826024492},
{"learn":[7.189853356],"iteration":578,"passed_time":0.7993697266,"remaining_time":0.5812342917},
{"learn":[7.189566415],"iteration":579,"passed_time":0.8006690149,"remaining_time":0.5797948039},
{"learn":[7.188191844],"iteration":580,"passed_time":0.8021294277,"remaining_time":0.5784719969},
{"learn":[7.187741879],"iteration":581,"passed_time":0.8035872457,"remaining_time":0.5771468534},
{"learn":[7.186496047],"iteration":582,"passed_time":0.8049995795,"remaining_time":0.5757887215},
{"learn":[7.18624273],"iteration":583,"passed_time":0.8063110824,"remaining_time":0.5743585793},
{"learn":[7.18598815],"iteration":584,"passed_time":0.807630394,"remaining_time":0.5729343821},
{"learn":[7.1857586],"iteration":585,"passed_time":0.8089749751,"remaining_time":0.5715283954},
{"learn":[7.185192289],"iteration":586,"passed_time":0.8103528072,"remaining_time":0.5701460126},
{"learn":[7.184452214],"iteration":587,"passed_time":0.8116701697,"remaining_time":0.5687212754},
{"learn":[7.184273295],"iteration":588,"passed_time":0.8130397456,"remaining_time":0.5673333369},
{"learn":[7.183090045],"iteration":589,"passed_time":0.8144193917,"remaining_time":0.5659524586},
{"learn":[7.182179659],"iteration":590,"passed_time":0.815787439,"remaining_time":0.5645635576},
{"learn":[7.180991347],"iteration":591,"passed_time":0.8173193534,"remaining_time":0.5632876625},
{"learn":[7.180855048],"iteration":592,"passed_time":0.8185971505,"remaining_time":0.5618364928},
{"learn":[7.180634442],"iteration":593,"passed_time":0.8198963324,"remaining_time":0.5604005235},
{"learn":[7.180455541],"iteration":594,"passed_time":0.8211339097,"remaining_time":0.5589230814},
{"learn":[7.180307146],"iteration":595,"passed_time":0.8224600053,"remaining_time":0.5575064466},
{"learn":[7.178757184],"iteration":596,"passed_time":0.8238789171,"remaining_time":0.5561527698},
{"learn":[7.178176747],"iteration":597,"passed_time":0.8252537137,"remaining_time":0.5547692189},
{"learn":[7.177894061],"iteration":598,"passed_time":0.8265193413,"remaining_time":0.5533126141},
{"learn":[7.176257658],"iteration":599,"passed_time":0.8279176488,"remaining_time":0.5519450992},
{"learn":[7.176058635],"iteration":600,"passed_time":0.8292293825,"remaining_time":0.550520006},
{"learn":[7.175926023],"iteration":601,"passed_time":0.8307142299,"remaining_time":0.54920974},
{"learn":[7.174702747],"iteration":602,"passed_time":0.8320499405,"remaining_time":0.5478007071},
{"learn":[7.174389325],"iteration":603,"passed_time":0.833373979,"remaining_time":0.5463842644},
{"learn":[7.174172459],"iteration":604,"passed_time":0.8346825398,"remaining_time":0.5449580219},
{"learn":[7.173949514],"iteration":605,"passed_time":0.8359608813,"remaining_time":0.5435125202},
{"learn":[7.173362391],"iteration":606,"passed_time":0.8373449055,"remaining_time":0.5421359932},
{"learn":[7.172079263],"iteration":607,"passed_time":0.8387153293,"remaining_time":0.5407506729},
{"learn":[7.170536991],"iteration":608,"passed_time":0.8401034856,"remaining_time":0.5393767863},
{"learn":[7.169422171],"iteration":609,"passed_time":0.8415523119,"remaining_time":0.538041642},
{"learn":[7.169258505],"iteration":610,"passed_time":0.8429454211,"remaining_time":0.5366706527},
{"learn":[7.165798661],"iteration":611,"passed_time":0.8445066239,"remaining_time":0.5354061602},
{"learn":[7.165015669],"iteration":612,"passed_time":0.8458803467,"remaining_time":0.5340223396},
{"learn":[7.164336827],"iteration":613,"passed_time":0.8472065782,"remaining_time":0.5326086957},
{"learn":[7.162680411],"iteration":614,"passed_time":0.8486604883,"remaining_time":0.531275265},
{"learn":[7.162153095],"iteration":615,"passed_time":0.8499843721,"remaining_time":0.5298603878},
{"learn":[7.161399541],"iteration":616,"passed_time":0.8513415925,"remaining_time":0.5284664991},
{"learn":[7.161175442],"iteration":617,"passed_time":0.8526855439,"remaining_time":0.5270645272},
{"learn":[7.158941012],"iteration":618,"passed_time":0.8539751089,"remaining_time":0.5256292673},
{"learn":[7.158795402],"iteration":619,"passed_time":0.8552976767,"remaining_time":0.5242147051},
{"learn":[7.158510058],"iteration":620,"passed_time":0.8565666994,"remaining_time":0.5227677602},
{"learn":[7.157122327],"iteration":621,"passed_time":0.8580962875,"remaining_time":0.5214797374},
{"learn":[7.155873098],"iteration":622,"passed_time":0.8595306504,"remaining_time":0.5201333149},
{"learn":[7.154736403],"iteration":623,"passed_time":0.8609093729,"remaining_time":0.5187530836},
{"learn":[7.154488464],"iteration":624,"passed_time":0.8621788007,"remaining_time":0.5173072804},
{"learn":[7.152754203],"iteration":625,"passed_time":0.8635015776,"remaining_time":0.5158939138},
{"learn":[7.152597136],"iteration":626,"passed_time":0.8648309827,"remaining_time":0.5144847792},
{"learn":[7.1519425],"iteration":627,"passed_time":0.8661683855,"remaining_time":0.513080636},
{"learn":[7.151163046],"iteration":628,"passed_time":0.8674946281,"remaining_time":0.5116701224},
{"learn":[7.151012946],"iteration":629,"passed_time":0.8688362631,"remaining_time":0.5102689165},
{"learn":[7.14918305],"iteration":630,"passed_time":0.870195673,"remaining_time":0.5088782937},
{"learn":[7.148951682],"iteration":631,"passed_time":0.8716912558,"remaining_time":0.5075670604},
{"learn":[7.148205237],"iteration":632,"passed_time":0.8730731616,"remaining_time":0.506189337},
{"learn":[7.14642625],"iteration":633,"passed_time":0.8744171439,"remaining_time":0.5047897077},
{"learn":[7.145346326],"iteration":634,"passed_time":0.8758241004,"remaining_time":0.5034264514},
{"learn":[7.14201994],"iteration":635,"passed_time":0.8771617393,"remaining_time":0.5020233854},
{"learn":[7.14145658],"iteration":636,"passed_time":0.8785669647,"remaining_time":0.5006590395},
{"learn":[7.141241754],"iteration":637,"passed_time":0.8799107244,"remaining_time":0.49925969},
{"learn":[7.140369326],"iteration":638,"passed_time":0.8812771142,"remaining_time":0.4978732993},
{"learn":[7.139353038],"iteration":639,"passed_time":0.8826101814,"remaining_time":0.496468227},
{"learn":[7.137247266],"iteration":640,"passed_time":0.8840430265,"remaining_time":0.4951192613},
{"learn":[7.137117129],"iteration":641,"passed_time":0.8853745527,"remaining_time":0.4937135356},
{"learn":[7.136954676],"iteration":642,"passed_time":0.8868729396,"remaining_time":0.4924006834},
{"learn":[7.134926049],"iteration":643,"passed_time":0.8883235699,"remaining_time":0.4910608554},
{"learn":[7.134579169],"iteration":644,"passed_time":0.8896578952,"remaining_time":0.489656671},
{"learn":[7.134240492],"iteration":645,"passed_time":0.8910284313,"remaining_time":0.4882725459},
{"learn":[7.134025702],"iteration":646,"passed_time":0.8924578192,"remaining_time":0.4869205721},
{"learn":[7.132657149],"iteration":647,"passed_time":0.8938777688,"remaining_time":0.4855632324},
{"learn":[7.132129972],"iteration":648,"passed_time":0.895196859,"remaining_time":0.4841511518},
{"learn":[7.131843771],"iteration":649,"passed_time":0.8966710898,"remaining_time":0.4828228945},
{"learn":[7.131091379],"iteration":650,"passed_time":0.8981449881,"remaining_time":0.4814940105},
{"learn":[7.130072108],"iteration":651,"passed_time":0.8996051417,"remaining_time":0.4801573455},
{"learn":[7.129506687],"iteration":652,"passed_time":0.9010732332,"remaining_time":0.4788245205},
{"learn":[7.129191476],"iteration":653,"passed_time":0.9024659639,"remaining_time":0.4774514121},
{"learn":[7.128482714],"iteration":654,"passed_time":0.9039976399,"remaining_time":0.4761514286},
{"learn":[7.128306907],"iteration":655,"passed_time":0.905400322,"remaining_time":0.4747830957},
{"learn":[7.127041095],"iteration":656,"passed_time":0.9069418966,"remaining_time":0.4734871698},
{"learn":[7.126950933],"iteration":657,"passed_time":0.9082822092,"remaining_time":0.4720858899},
{"learn":[7.125368917],"iteration":658,"passed_time":0.9095967245,"remaining_time":0.4706714462},
{"learn":[7.124659629],"iteration":659,"passed_time":0.9111499682,"remaining_time":0.4693802866},
{"learn":[7.122170018],"iteration":660,"passed_time":0.9124888524,"remaining_time":0.4679783978},
{"learn":[7.122054569],"iteration":661,"passed_time":0.913872744,"remaining_time":0.4665996789},
{"learn":[7.121287127],"iteration":662,"passed_time":0.915385759,"remaining_time":0.4652865773},
{"learn":[7.12097815],"iteration":663,"passed_time":0.9168539188,"remaining_time":0.4639501758},
{"learn":[7.119344017],"iteration":664,"passed_time":0.9183350378,"remaining_time":0.4626199062},
{"learn":[7.119172142],"iteration":665,"passed_time":0.9197627899,"remaining_time":0.4612624202},
{"learn":[7.118612615],"iteration":666,"passed_time":0.9212241425,"remaining_time":0.4599214985},
{"learn":[7.117898504],"iteration":667,"passed_time":0.9226029206,"remaining_time":0.4585391761},
{"learn":[7.11766045],"iteration":668,"passed_time":0.9238909103,"remaining_time":0.4571119451},
{"learn":[7.11657036],"iteration":669,"passed_time":0.9253296748,"remaining_time":0.4557593921},
{"learn":[7.115266244],"iteration":670,"passed_time":0.926773157,"remaining_time":0.4544088952},
{"learn":[7.113601812],"iteration":671,"passed_time":0.9282751102,"remaining_time":0.4530866609},
{"learn":[7.11305949],"iteration":672,"passed_time":0.9296954966,"remaining_time":0.4517242606},
{"learn":[7.112503483],"iteration":673,"passed_time":0.9310739351,"remaining_time":0.4503413989},
{"learn":[7.112348038],"iteration":674,"passed_time":0.9325493334,"remaining_time":0.4490052346},
{"learn":[7.112122924],"iteration":675,"passed_time":0.9340715097,"remaining_time":0.4476910786},
{"learn":[7.111942483],"iteration":676,"passed_time":0.9355074479,"remaining_time":0.4463351635},
{"learn":[7.111721002],"iteration":677,"passed_time":0.9370977188,"remaining_time":0.4450523089},
{"learn":[7.110532869],"iteration":678,"passed_time":0.9386115841,"remaining_time":0.4437324278},
{"learn":[7.110366616],"iteration":679,"passed_time":0.9399901947,"remaining_time":0.4423483269},
{"learn":[7.110161174],"iteration":680,"passed_time":0.9413880416,"remaining_time":0.440973253},
{"learn":[7.109605421],"iteration":681,"passed_time":0.9428479513,"remaining_time":0.4396270506},
{"learn":[7.107936012],"iteration":682,"passed_time":0.9448540798,"remaining_time":0.4385340312},
{"learn":[7.106216504],"iteration":683,"passed_time":0.9464430683,"remaining_time":0.4372456281},
{"learn":[7.105501001],"iteration":684,"passed_time":0.9479911638,"remaining_time":0.4359375425},
{"learn":[7.104279246],"iteration":685,"passed_time":0.9495711553,"remaining_time":0.4346433568},
{"learn":[7.104075869],"iteration":686,"passed_time":0.9510561409,"remaining_time":0.433305054},
{"learn":[7.101594042],"iteration":687,"passed_time":0.9524000661,"remaining_time":0.4319023555},
{"learn":[7.10104204],"iteration":688,"passed_time":0.9537270043,"remaining_time":0.4304921601},
{"learn":[7.09978409],"iteration":689,"passed_time":0.9550675614,"remaining_time":0.4290883247},
{"learn":[7.097011265],"iteration":690,"passed_time":0.9564305416,"remaining_time":0.4276946995},
{"learn":[7.096851607],"iteration":691,"passed_time":0.9578308522,"remaining_time":0.4263177781},
{"learn":[7.096174735],"iteration":692,"passed_time":0.9593887263,"remaining_time":0.4250105901},
{"learn":[7.095966495],"iteration":693,"passed_time":0.9608929519,"remaining_time":0.4236790249},
{"learn":[7.095753515],"iteration":694,"passed_time":0.9624115966,"remaining_time":0.4223532906},
{"learn":[7.094484264],"iteration":695,"passed_time":0.963873913,"remaining_time":0.4210023988},
{"learn":[7.09433312],"iteration":696,"passed_time":0.9652746788,"remaining_time":0.41962443},
{"learn":[7.092928328],"iteration":697,"passed_time":0.9667508564,"remaining_time":0.4182790238},
{"learn":[7.092803208],"iteration":698,"passed_time":0.9683061935,"remaining_time":0.4169673308},
{"learn":[7.090146196],"iteration":699,"passed_time":0.9699283056,"remaining_time":0.4156835595},
{"learn":[7.088948018],"iteration":700,"passed_time":0.9713669645,"remaining_time":0.414320574},
{"learn":[7.087614472],"iteration":701,"passed_time":0.9729118138,"remaining_time":0.4130024509},
{"learn":[7.087449625],"iteration":702,"passed_time":0.9743732914,"remaining_time":0.4116484603},
{"learn":[7.087272549],"iteration":703,"passed_time":0.9758152775,"remaining_time":0.4102859689},
{"learn":[7.086588975],"iteration":704,"passed_time":0.9772565208,"remaining_time":0.4089229413},
{"learn":[7.086455303],"iteration":705,"passed_time":0.97868034,"remaining_time":0.4075524362},
{"learn":[7.085074858],"iteration":706,"passed_time":0.9801686076,"remaining_time":0.4062084894},
{"learn":[7.083455803],"iteration":707,"passed_time":0.9817626417,"remaining_time":0.4049077562},
{"learn":[7.083062503],"iteration":708,"passed_time":0.9832570894,"remaining_time":0.4035653216},
{"learn":[7.081705102],"iteration":709,"passed_time":0.9848399838,"remaining_time":0.4022585849},
{"learn":[7.081175909],"iteration":710,"passed_time":0.9863041219,"remaining_time":0.4009028006},
{"learn":[7.07938637],"iteration":711,"passed_time":0.9878792685,"remaining_time":0.3995916142},
{"learn":[7.078271724],"iteration":712,"passed_time":0.9894813829,"remaining_time":0.3982905426},
{"learn":[7.076781722],"iteration":713,"passed_time":0.9910423234,"remaining_time":0.3969721351},
{"learn":[7.076095017],"iteration":714,"passed_time":0.9926701477,"remaining_time":0.3956797092},
{"learn":[7.074753945],"iteration":715,"passed_time":0.9943587272,"remaining_time":0.3944104448},
{"learn":[7.074340109],"iteration":716,"passed_time":0.9959462002,"remaining_time":0.3931001041},
{"learn":[7.073284106],"iteration":717,"passed_time":0.9976157741,"remaining_time":0.3918212372},
{"learn":[7.071928401],"iteration":718,"passed_time":0.9992321617,"remaining_time":0.3905204971},
{"learn":[7.071404651],"iteration":719,"passed_time":1.000800286,"remaining_time":0.3892001112},
{"learn":[7.070262253],"iteration":720,"passed_time":1.00227625,"remaining_time":0.3878433757},
{"learn":[7.069729762],"iteration":721,"passed_time":1.003913596,"remaining_time":0.3865484482},
{"learn":[7.067405278],"iteration":722,"passed_time":1.005573616,"remaining_time":0.3852612607},
{"learn":[7.066197969],"iteration":723,"passed_time":1.007254586,"remaining_time":0.3839810301},
{"learn":[7.065647048],"iteration":724,"passed_time":1.008689434,"remaining_time":0.382606337},
{"learn":[7.065318657],"iteration":725,"passed_time":1.010354765,"remaining_time":0.381318465},
{"learn":[7.06504398],"iteration":726,"passed_time":1.011741842,"remaining_time":0.3799250657},
{"learn":[7.064505756],"iteration":727,"passed_time":1.013292767,"remaining_time":0.3785929019},
{"learn":[7.064303494],"iteration":728,"passed_time":1.014732158,"remaining_time":0.3772186759},
{"learn":[7.063591418],"iteration":729,"passed_time":1.01629176,"remaining_time":0.3758887332},
{"learn":[7.062847335],"iteration":730,"passed_time":1.018076549,"remaining_time":0.3746410284},
{"learn":[7.062615546],"iteration":731,"passed_time":1.019684271,"remaining_time":0.3733270281},
{"learn":[7.06248426],"iteration":732,"passed_time":1.021241864,"remaining_time":0.3719939669},
{"learn":[7.059992133],"iteration":733,"passed_time":1.022894514,"remaining_time":0.370694742},
{"learn":[7.059580772],"iteration":734,"passed_time":1.024174494,"remaining_time":0.3692601917},
{"learn":[7.057841927],"iteration":735,"passed_time":1.025883469,"remaining_time":0.3679799401},
{"learn":[7.057674672],"iteration":736,"passed_time":1.027626858,"remaining_time":0.3667108057},
{"learn":[7.05618994],"iteration":737,"passed_time":1.029173106,"remaining_time":0.365370398},
{"learn":[7.055632859],"iteration":738,"passed_time":1.030734322,"remaining_time":0.3640347199},
{"learn":[7.055479425],"iteration":739,"passed_time":1.032336513,"remaining_time":0.362712829},
{"learn":[7.055262648],"iteration":740,"passed_time":1.033732099,"remaining_time":0.3613179673},
{"learn":[7.055147203],"iteration":741,"passed_time":1.035066278,"remaining_time":0.3599017515},
{"learn":[7.054963896],"iteration":742,"passed_time":1.036478052,"remaining_time":0.3585125967},
{"learn":[7.054682666],"iteration":743,"passed_time":1.037843048,"remaining_time":0.3571072852},
{"learn":[7.054133962],"iteration":744,"passed_time":1.039326806,"remaining_time":0.3557427321},
{"learn":[7.053141009],"iteration":745,"passed_time":1.040808441,"remaining_time":0.3543771366},
{"learn":[7.052961922],"iteration":746,"passed_time":1.042147134,"remaining_time":0.3529628179},
{"learn":[7.052803759],"iteration":747,"passed_time":1.043470931,"remaining_time":0.3515436828},
{"learn":[7.051655756],"iteration":748,"passed_time":1.044966026,"remaining_time":0.3501822062},
{"learn":[7.050935317],"iteration":749,"passed_time":1.046631898,"remaining_time":0.3488772994},
{"learn":[7.050641678],"iteration":750,"passed_time":1.048011179,"remaining_time":0.3474764097},
{"learn":[7.050004074],"iteration":751,"passed_time":1.049453415,"remaining_time":0.3460963391},
{"learn":[7.049524955],"iteration":752,"passed_time":1.051023016,"remaining_time":0.3447578816},
{"learn":[7.049133011],"iteration":753,"passed_time":1.052750079,"remaining_time":0.3434701848},
{"learn":[7.047400914],"iteration":754,"passed_time":1.053887954,"remaining_time":0.3419901308},
{"learn":[7.046723999],"iteration":755,"passed_time":1.055334703,"remaining_time":0.3406106714},
{"learn":[7.046385154],"iteration":756,"passed_time":1.056852987,"remaining_time":0.3392539971},
{"learn":[7.045648007],"iteration":757,"passed_time":1.058435292,"remaining_time":0.3379173361},
{"learn":[7.044495189],"iteration":758,"passed_time":1.059881863,"remaining_time":0.3365369289},
{"learn":[7.044211297],"iteration":759,"passed_time":1.061448931,"remaining_time":0.3351943993},
{"learn":[7.043753048],"iteration":760,"passed_time":1.062845919,"remaining_time":0.3337978642},
{"learn":[7.043581151],"iteration":761,"passed_time":1.064218145,"remaining_time":0.3323935938},
{"learn":[7.042705465],"iteration":762,"passed_time":1.0656737,"remaining_time":0.3310152909},
{"learn":[7.042440308],"iteration":763,"passed_time":1.067337221,"remaining_time":0.3297010263},
{"learn":[7.042271766],"iteration":764,"passed_time":1.068673126,"remaining_time":0.3282852086},
{"learn":[7.0421231],"iteration":765,"passed_time":1.06997933,"remaining_time":0.3268605265},
{"learn":[7.041247983],"iteration":766,"passed_time":1.071476535,"remaining_time":0.3254941756},
{"learn":[7.039780993],"iteration":767,"passed_time":1.073038692,"remaining_time":0.324147105},
{"learn":[7.039276809],"iteration":768,"passed_time":1.074585619,"remaining_time":0.3227948998},
{"learn":[7.039158126],"iteration":769,"passed_time":1.076221243,"remaining_time":0.3214686831},
{"learn":[7.039017233],"iteration":770,"passed_time":1.077881043,"remaining_time":0.320148844},
{"learn":[7.037724148],"iteration":771,"passed_time":1.0793491,"remaining_time":0.318771496},
{"learn":[7.037489814],"iteration":772,"passed_time":1.080847093,"remaining_time":0.3174027039},
{"learn":[7.036363386],"iteration":773,"passed_time":1.082243584,"remaining_time":0.3160039406},
{"learn":[7.03627743],"iteration":774,"passed_time":1.083683662,"remaining_time":0.3146178374},
{"learn":[7.035797925],"iteration":775,"passed_time":1.085092304,"remaining_time":0.3132225209},
{"learn":[7.035704757],"iteration":776,"passed_time":1.086651033,"remaining_time":0.3118702449},
{"learn":[7.034933588],"iteration":777,"passed_time":1.088183796,"remaining_time":0.3105100293},
{"learn":[7.034817192],"iteration":778,"passed_time":1.089650985,"remaining_time":0.3091307674},
{"learn":[7.034268793],"iteration":779,"passed_time":1.091088424,"remaining_time":0.3077428887},
{"learn":[7.03402712],"iteration":780,"passed_time":1.092522644,"remaining_time":0.3063539809},
{"learn":[7.033808553],"iteration":781,"passed_time":1.094082958,"remaining_time":0.3050001085},
{"learn":[7.033503518],"iteration":782,"passed_time":1.09563587,"remaining_time":0.3036436573},
{"learn":[7.033317326],"iteration":783,"passed_time":1.097066888,"remaining_time":0.3022531223},
{"learn":[7.032692382],"iteration":784,"passed_time":1.098407677,"remaining_time":0.3008377714},
{"learn":[7.032469021],"iteration":785,"passed_time":1.099947937,"remaining_time":0.2994769194},
{"learn":[7.03176917],"iteration":786,"passed_time":1.101432864,"remaining_time":0.2981006355},
{"learn":[7.031499682],"iteration":787,"passed_time":1.102844596,"remaining_time":0.2967043836},
{"learn":[7.031411963],"iteration":788,"passed_time":1.1043771,"remaining_time":0.2953403905},
{"learn":[7.03051706],"iteration":789,"passed_time":1.106324686,"remaining_time":0.294086309},
{"learn":[7.029669521],"iteration":790,"passed_time":1.107945683,"remaining_time":0.2927441817},
{"learn":[7.028427908],"iteration":791,"passed_time":1.109349574,"remaining_time":0.2913443327},
{"learn":[7.027272795],"iteration":792,"passed_time":1.110964064,"remaining_time":0.2899994467},
{"learn":[7.025802598],"iteration":793,"passed_time":1.112369233,"remaining_time":0.2885995744},
{"learn":[7.025606881],"iteration":794,"passed_time":1.114034164,"remaining_time":0.2872666713},
{"learn":[7.025363501],"iteration":795,"passed_time":1.11547124,"remaining_time":0.2858745389},
{"learn":[7.025012015],"iteration":796,"passed_time":1.117143654,"remaining_time":0.2845422356},
{"learn":[7.024804286],"iteration":797,"passed_time":1.118717842,"remaining_time":0.2831842155},
{"learn":[7.024690101],"iteration":798,"passed_time":1.120118996,"remaining_time":0.2817821253},
{"learn":[7.023760117],"iteration":799,"passed_time":1.121708011,"remaining_time":0.2804270028},
{"learn":[7.022283433],"iteration":800,"passed_time":1.123131125,"remaining_time":0.2790300797},
{"learn":[7.022174175],"iteration":801,"passed_time":1.124626114,"remaining_time":0.2776508362},
{"learn":[7.021614274],"iteration":802,"passed_time":1.126293474,"remaining_time":0.2763135921},
{"learn":[7.020770098],"iteration":803,"passed_time":1.12793151,"remaining_time":0.2749683782},
{"learn":[7.020175407],"iteration":804,"passed_time":1.129414277,"remaining_time":0.2735848248},
{"learn":[7.020070894],"iteration":805,"passed_time":1.130910137,"remaining_time":0.272204177},
{"learn":[7.019945123],"iteration":806,"passed_time":1.132401092,"remaining_time":0.2708220704},
{"learn":[7.019171505],"iteration":807,"passed_time":1.133943543,"remaining_time":0.2694519311},
{"learn":[7.017828042],"iteration":808,"passed_time":1.135667205,"remaining_time":0.2681241485},
{"learn":[7.017730428],"iteration":809,"passed_time":1.137133002,"remaining_time":0.2667349017},
{"learn":[7.017402902],"iteration":810,"passed_time":1.138633363,"remaining_time":0.2653535212},
{"learn":[7.017328289],"iteration":811,"passed_time":1.140119826,"remaining_time":0.2639686296},
{"learn":[7.017240517],"iteration":812,"passed_time":1.141660973,"remaining_time":0.2625960663},
{"learn":[7.015719557],"iteration":813,"passed_time":1.143225769,"remaining_time":0.2612284927},
{"learn":[7.015646599],"iteration":814,"passed_time":1.144543758,"remaining_time":0.2598044113},
{"learn":[7.015296367],"iteration":815,"passed_time":1.14607331,"remaining_time":0.2584282954},
{"learn":[7.014260742],"iteration":816,"passed_time":1.147755251,"remaining_time":0.2570859374},
{"learn":[7.013737647],"iteration":817,"passed_time":1.14920443,"remaining_time":0.2556909611},
{"learn":[7.013565733],"iteration":818,"passed_time":1.15063894,"remaining_time":0.2542926108},
{"learn":[7.013220643],"iteration":819,"passed_time":1.151993308,"remaining_time":0.2528765798},
{"learn":[7.012867133],"iteration":820,"passed_time":1.153653193,"remaining_time":0.2515273099},
{"learn":[7.011779328],"iteration":821,"passed_time":1.155439777,"remaining_time":0.2502047205},
{"learn":[7.010578771],"iteration":822,"passed_time":1.156947599,"remaining_time":0.248821051},
{"learn":[7.010529928],"iteration":823,"passed_time":1.158537714,"remaining_time":0.2474546574},
{"learn":[7.009357111],"iteration":824,"passed_time":1.160055133,"remaining_time":0.2460723009},
{"learn":[7.009191507],"iteration":825,"passed_time":1.161500215,"remaining_time":0.2446743795},
{"learn":[7.008338151],"iteration":826,"passed_time":1.163057313,"remaining_time":0.2432997764},
{"learn":[7.007325813],"iteration":827,"passed_time":1.164604501,"remaining_time":0.2419226742},
{"learn":[7.007227682],"iteration":828,"passed_time":1.166075325,"remaining_time":0.2405294096},
{"learn":[7.005985153],"iteration":829,"passed_time":1.167867435,"remaining_time":0.2392017638},
{"learn":[7.004404644],"iteration":830,"passed_time":1.169363174,"remaining_time":0.2378127272},
{"learn":[7.003913406],"iteration":831,"passed_time":1.170806775,"remaining_time":0.2364129064},
{"learn":[7.002863225],"iteration":832,"passed_time":1.172306576,"remaining_time":0.2350242475},
{"learn":[7.002440038],"iteration":833,"passed_time":1.173723558,"remaining_time":0.2336188377},
{"learn":[7.001477701],"iteration":834,"passed_time":1.175348537,"remaining_time":0.2322545012},
{"learn":[7.001330824],"iteration":835,"passed_time":1.176925058,"remaining_time":0.2308800353},
{"learn":[7.00118716],"iteration":836,"passed_time":1.178298606,"remaining_time":0.2294655589},
{"learn":[7.000856701],"iteration":837,"passed_time":1.179798079,"remaining_time":0.2280755237},
{"learn":[7.000696702],"iteration":838,"passed_time":1.181168545,"remaining_time":0.2266604717},
{"learn":[6.999854728],"iteration":839,"passed_time":1.182742658,"remaining_time":0.2252843157},
{"learn":[6.999157032],"iteration":840,"passed_time":1.184226931,"remaining_time":0.2238907039},
{"learn":[6.998862579],"iteration":841,"passed_time":1.18570272,"remaining_time":0.2224952848},
{"learn":[6.998022197],"iteration":842,"passed_time":1.187262373,"remaining_time":0.2211152937},
{"learn":[6.997842706],"iteration":843,"passed_time":1.188853927,"remaining_time":0.2197407733},
{"learn":[6.996658404],"iteration":844,"passed_time":1.19046676,"remaining_time":0.2183696424},
{"learn":[6.996564779],"iteration":845,"passed_time":1.191903169,"remaining_time":0.216965825},
{"learn":[6.995877281],"iteration":846,"passed_time":1.193417594,"remaining_time":0.2155760235},
{"learn":[6.995423924],"iteration":847,"passed_time":1.194937009,"remaining_time":0.2141868224},
{"learn":[6.994269638],"iteration":848,"passed_time":1.196287078,"remaining_time":0.2127671952},
{"learn":[6.994029165],"iteration":849,"passed_time":1.197687338,"remaining_time":0.2113565891},
{"learn":[6.992822195],"iteration":850,"passed_time":1.199189795,"remaining_time":0.2099639007},
{"learn":[6.992494088],"iteration":851,"passed_time":1.200686022,"remaining_time":0.2085698724},
{"learn":[6.992372658],"iteration":852,"passed_time":1.202069733,"remaining_time":0.2071562143},
{"learn":[6.992104689],"iteration":853,"passed_time":1.203633064,"remaining_time":0.2057733341},
{"learn":[6.991930363],"iteration":854,"passed_time":1.20507162,"remaining_time":0.2043688712},
{"learn":[6.989955642],"iteration":855,"passed_time":1.206698215,"remaining_time":0.2029959614},
{"learn":[6.98898121],"iteration":856,"passed_time":1.208087624,"remaining_time":0.2015828823},
{"learn":[6.988766944],"iteration":857,"passed_time":1.209369362,"remaining_time":0.200152039},
{"learn":[6.988607585],"iteration":858,"passed_time":1.210837757,"remaining_time":0.1987521813},
{"learn":[6.987595693],"iteration":859,"passed_time":1.212289924,"remaining_time":0.1973495225},
{"learn":[6.985796415],"iteration":860,"passed_time":1.213605513,"remaining_time":0.1959246995},
{"learn":[6.984654572],"iteration":861,"passed_time":1.215260193,"remaining_time":0.194554416},
{"learn":[6.984220837],"iteration":862,"passed_time":1.216520691,"remaining_time":0.1931208977},
{"learn":[6.984127706],"iteration":863,"passed_time":1.217966486,"remaining_time":0.1917169468},
{"learn":[6.983997512],"iteration":864,"passed_time":1.219385614,"remaining_time":0.1903087374},
{"learn":[6.983794781],"iteration":865,"passed_time":1.220932336,"remaining_time":0.1889202459},
{"learn":[6.983415898],"iteration":866,"passed_time":1.222571387,"remaining_time":0.187545553},
{"learn":[6.982981429],"iteration":867,"passed_time":1.224073964,"remaining_time":0.1861494968},
{"learn":[6.982792692],"iteration":868,"passed_time":1.225527742,"remaining_time":0.1847458391},
{"learn":[6.981910094],"iteration":869,"passed_time":1.226950785,"remaining_time":0.1833374736},
{"learn":[6.980522917],"iteration":870,"passed_time":1.228315038,"remaining_time":0.1819203673},
{"learn":[6.979834564],"iteration":871,"passed_time":1.229866706,"remaining_time":0.1805308927},
{"learn":[6.979673012],"iteration":872,"passed_time":1.231163157,"remaining_time":0.1791039186},
{"learn":[6.979561844],"iteration":873,"passed_time":1.232599939,"remaining_time":0.1776974741},
{"learn":[6.978276503],"iteration":874,"passed_time":1.23405059,"remaining_time":0.1762929415},
{"learn":[6.978040706],"iteration":875,"passed_time":1.235456777,"remaining_time":0.1748820095},
{"learn":[6.977859364],"iteration":876,"passed_time":1.237286205,"remaining_time":0.1735304484},
{"learn":[6.97755791],"iteration":877,"passed_time":1.238700908,"remaining_time":0.1721201718},
{"learn":[6.976699457],"iteration":878,"passed_time":1.24014557,"remaining_time":0.1707140091},
{"learn":[6.975326298],"iteration":879,"passed_time":1.241572188,"remaining_time":0.1693052983},
{"learn":[6.975246651],"iteration":880,"passed_time":1.242898349,"remaining_time":0.1678829779},
{"learn":[6.974383373],"iteration":881,"passed_time":1.244233907,"remaining_time":0.1664621326},
{"learn":[6.972727664],"iteration":882,"passed_time":1.245776158,"remaining_time":0.165068868},
{"learn":[6.972430314],"iteration":883,"passed_time":1.247238891,"remaining_time":0.1636648318},
{"learn":[6.972178517],"iteration":884,"passed_time":1.248675155,"remaining_time":0.1622572235},
{"learn":[6.971407133],"iteration":885,"passed_time":1.250234314,"remaining_time":0.1608653631},
{"learn":[6.971099102],"iteration":886,"passed_time":1.251650532,"remaining_time":0.1594549156},
{"learn":[6.970371723],"iteration":887,"passed_time":1.253181161,"remaining_time":0.1580588852},
{"learn":[6.970088462],"iteration":888,"passed_time":1.254647606,"remaining_time":0.156654538},
{"learn":[6.968230938],"iteration":889,"passed_time":1.256105352,"remaining_time":0.1552489761},
{"learn":[6.967459362],"iteration":890,"passed_time":1.257531781,"remaining_time":0.1538394659},
{"learn":[6.966959632],"iteration":891,"passed_time":1.258881026,"remaining_time":0.1524205727},
{"learn":[6.966834726],"iteration":892,"passed_time":1.260273864,"remaining_time":0.1510070587},
{"learn":[6.966691882],"iteration":893,"passed_time":1.26184043,"remaining_time":0.1496141897},
{"learn":[6.966568769],"iteration":894,"passed_time":1.263391551,"remaining_time":0.1482191205},
{"learn":[6.965627812],"iteration":895,"passed_time":1.264875863,"remaining_time":0.1468159483},
{"learn":[6.964227556],"iteration":896,"passed_time":1.266403726,"remaining_time":0.1454175962},
{"learn":[6.964139672],"iteration":897,"passed_time":1.268549662,"remaining_time":0.1440891599},
{"learn":[6.963284716],"iteration":898,"passed_time":1.270208875,"remaining_time":0.1427042229},
{"learn":[6.963098458],"iteration":899,"passed_time":1.271681091,"remaining_time":0.141297899},
{"learn":[6.962942737],"iteration":900,"passed_time":1.273240212,"remaining_time":0.1399009778},
{"learn":[6.962878913],"iteration":901,"passed_time":1.274751245,"remaining_time":0.1384984722},
{"learn":[6.962816359],"iteration":902,"passed_time":1.276157433,"remaining_time":0.137084464},
{"learn":[6.962734879],"iteration":903,"passed_time":1.277647826,"remaining_time":0.1356794151},
{"learn":[6.961988123],"iteration":904,"passed_time":1.279027154,"remaining_time":0.1342625189},
{"learn":[6.961331976],"iteration":905,"passed_time":1.2806419,"remaining_time":0.1328701309},
{"learn":[6.961216827],"iteration":906,"passed_time":1.282005454,"remaining_time":0.1314514964},
{"learn":[6.960987995],"iteration":907,"passed_time":1.283447049,"remaining_time":0.1300408905},
{"learn":[6.960639947],"iteration":908,"passed_time":1.284917026,"remaining_time":0.1286330576},
{"learn":[6.960344143],"iteration":909,"passed_time":1.286289927,"remaining_time":0.1272154873},
{"learn":[6.959679272],"iteration":910,"passed_time":1.287702731,"remaining_time":0.1258019133},
{"learn":[6.959266555],"iteration":911,"passed_time":1.289159898,"remaining_time":0.1243926217},
{"learn":[6.958608512],"iteration":912,"passed_time":1.290683916,"remaining_time":0.1229895955},
{"learn":[6.958256682],"iteration":913,"passed_time":1.292182205,"remaining_time":0.1215838837},
{"learn":[6.958139204],"iteration":914,"passed_time":1.293681827,"remaining_time":0.1201780932},
{"learn":[6.957641551],"iteration":915,"passed_time":1.295181328,"remaining_time":0.1187720868},
{"learn":[6.957534503],"iteration":916,"passed_time":1.296549138,"remaining_time":0.1173539569},
{"learn":[6.956883392],"iteration":917,"passed_time":1.29796546,"remaining_time":0.1159402699},
{"learn":[6.956381407],"iteration":918,"passed_time":1.299495468,"remaining_time":0.1145365973},
{"learn":[6.956220368],"iteration":919,"passed_time":1.300964188,"remaining_time":0.1131273207},
{"learn":[6.956065012],"iteration":920,"passed_time":1.302361583,"remaining_time":0.111711797},
{"learn":[6.955075125],"iteration":921,"passed_time":1.303806844,"remaining_time":0.1103003621},
{"learn":[6.954011657],"iteration":922,"passed_time":1.305237118,"remaining_time":0.1088876035},
{"learn":[6.95391548],"iteration":923,"passed_time":1.306634423,"remaining_time":0.1074720954},
{"learn":[6.953359689],"iteration":924,"passed_time":1.308091215,"remaining_time":0.1060614498},
{"learn":[6.953283229],"iteration":925,"passed_time":1.309511353,"remaining_time":0.1046477755},
{"learn":[6.953084491],"iteration":926,"passed_time":1.310982076,"remaining_time":0.1032380707},
{"learn":[6.952349598],"iteration":927,"passed_time":1.312451044,"remaining_time":0.1018280982},
{"learn":[6.952006769],"iteration":928,"passed_time":1.313901329,"remaining_time":0.1004165709},
{"learn":[6.951367072],"iteration":929,"passed_time":1.31529967,"remaining_time":0.09900105044},
{"learn":[6.950822189],"iteration":930,"passed_time":1.316745405,"remaining_time":0.09758907946},
{"learn":[6.949960011],"iteration":931,"passed_time":1.318278465,"remaining_time":0.09618340734},
{"learn":[6.949845408],"iteration":932,"passed_time":1.31988755,"remaining_time":0.09478292157},
{"learn":[6.948974281],"iteration":933,"passed_time":1.321370545,"remaining_time":0.09337307921},
{"learn":[6.948082431],"iteration":934,"passed_time":1.322832095,"remaining_time":0.09196158947},
{"learn":[6.947427675],"iteration":935,"passed_time":1.324356171,"remaining_time":0.09055426813},
{"learn":[6.947133106],"iteration":936,"passed_time":1.32583876,"remaining_time":0.08914390811},
{"learn":[6.946811085],"iteration":937,"passed_time":1.327303973,"remaining_time":0.08773224557},
{"learn":[6.946571735],"iteration":938,"passed_time":1.328754538,"remaining_time":0.08631951739},
{"learn":[6.946377907],"iteration":939,"passed_time":1.33023173,"remaining_time":0.08490840832},
{"learn":[6.945258351],"iteration":940,"passed_time":1.33172656,"remaining_time":0.08349826466},
{"learn":[6.944271066],"iteration":941,"passed_time":1.333401808,"remaining_time":0.08209904973},
{"learn":[6.944181805],"iteration":942,"passed_time":1.334862426,"remaining_time":0.080686276},
{"learn":[6.943544914],"iteration":943,"passed_time":1.336216674,"remaining_time":0.07926709085},
{"learn":[6.943475094],"iteration":944,"passed_time":1.337634312,"remaining_time":0.07785173246},
{"learn":[6.943248939],"iteration":945,"passed_time":1.339223762,"remaining_time":0.0764461767},
{"learn":[6.943038521],"iteration":946,"passed_time":1.340649589,"remaining_time":0.07503107521},
{"learn":[6.942081928],"iteration":947,"passed_time":1.342003764,"remaining_time":0.07361202079},
{"learn":[6.94139878],"iteration":948,"passed_time":1.343622308,"remaining_time":0.07220731054},
{"learn":[6.941053283],"iteration":949,"passed_time":1.345188766,"remaining_time":0.07079940874},
{"learn":[6.940966411],"iteration":950,"passed_time":1.346576882,"remaining_time":0.06938198447},
{"learn":[6.9408505],"iteration":951,"passed_time":1.348099255,"remaining_time":0.06797139098},
{"learn":[6.940587883],"iteration":952,"passed_time":1.349457569,"remaining_time":0.06655247191},
{"learn":[6.939811703],"iteration":953,"passed_time":1.350972252,"remaining_time":0.0651412197},
{"learn":[6.939518875],"iteration":954,"passed_time":1.352418954,"remaining_time":0.06372654757},
{"learn":[6.93888049],"iteration":955,"passed_time":1.353749226,"remaining_time":0.06230644975},
{"learn":[6.938467685],"iteration":956,"passed_time":1.355285291,"remaining_time":0.06089578632},
{"learn":[6.938150067],"iteration":957,"passed_time":1.356800445,"remaining_time":0.05948394435},
{"learn":[6.937887073],"iteration":958,"passed_time":1.358265042,"remaining_time":0.05806972547},
{"learn":[6.937804901],"iteration":959,"passed_time":1.35996538,"remaining_time":0.05666522417},
{"learn":[6.937707208],"iteration":960,"passed_time":1.361532041,"remaining_time":0.05525468222},
{"learn":[6.936850989],"iteration":961,"passed_time":1.363473097,"remaining_time":0.05385860466},
{"learn":[6.936792176],"iteration":962,"passed_time":1.365053809,"remaining_time":0.0524475503},
{"learn":[6.936022345],"iteration":963,"passed_time":1.366438765,"remaining_time":0.05102883356},
{"learn":[6.934497747],"iteration":964,"passed_time":1.36792186,"remaining_time":0.04961374624},
{"learn":[6.933071363],"iteration":965,"passed_time":1.369377641,"remaining_time":0.04819755673},
{"learn":[6.932603831],"iteration":966,"passed_time":1.370786404,"remaining_time":0.0467796808},
{"learn":[6.93219122],"iteration":967,"passed_time":1.37233425,"remaining_time":0.04536642148},
{"learn":[6.932129299],"iteration":968,"passed_time":1.373854472,"remaining_time":0.04395200066},
{"learn":[6.932074853],"iteration":969,"passed_time":1.375332084,"remaining_time":0.04253604382},
{"learn":[6.931017091],"iteration":970,"passed_time":1.37682271,"remaining_time":0.04112034871},
{"learn":[6.930073405],"iteration":971,"passed_time":1.378244108,"remaining_time":0.03970250518},
{"learn":[6.929954922],"iteration":972,"passed_time":1.379695277,"remaining_time":0.03828548046},
{"learn":[6.929879211],"iteration":973,"passed_time":1.38112066,"remaining_time":0.03686769728},
{"learn":[6.928532317],"iteration":974,"passed_time":1.382561792,"remaining_time":0.03545030237},
{"learn":[6.928278409],"iteration":975,"passed_time":1.384151716,"remaining_time":0.03403651761},
{"learn":[6.927421541],"iteration":976,"passed_time":1.385649242,"remaining_time":0.03262019711},
{"learn":[6.927339255],"iteration":977,"passed_time":1.387241408,"remaining_time":0.03120583944},
{"learn":[6.926611733],"iteration":978,"passed_time":1.388689245,"remaining_time":0.02978802262},
{"learn":[6.925246186],"iteration":979,"passed_time":1.390151141,"remaining_time":0.02837043146},
{"learn":[6.92497031],"iteration":980,"passed_time":1.391541119,"remaining_time":0.02695135705},
{"learn":[6.924770831],"iteration":981,"passed_time":1.392961633,"remaining_time":0.02553290163},
{"learn":[6.924102598],"iteration":982,"passed_time":1.394274664,"remaining_time":0.0241125832},
{"learn":[6.924053556],"iteration":983,"passed_time":1.395774064,"remaining_time":0.02269551323},
{"learn":[6.92334582],"iteration":984,"passed_time":1.397269016,"remaining_time":0.02127820837},
{"learn":[6.922387715],"iteration":985,"passed_time":1.398700304,"remaining_time":0.01985984204},
{"learn":[6.921764889],"iteration":986,"passed_time":1.400034943,"remaining_time":0.01844017655},
{"learn":[6.921616937],"iteration":987,"passed_time":1.401493623,"remaining_time":0.01702218976},
{"learn":[6.920911929],"iteration":988,"passed_time":1.402966073,"remaining_time":0.01560427382},
{"learn":[6.920819292],"iteration":989,"passed_time":1.404348368,"remaining_time":0.01418533705},
{"learn":[6.920611138],"iteration":990,"passed_time":1.405771266,"remaining_time":0.01276684298},
{"learn":[6.9193726],"iteration":991,"passed_time":1.407284367,"remaining_time":0.01134906748},
{"learn":[6.919274316],"iteration":992,"passed_time":1.408749783,"remaining_time":0.009930763824},
{"learn":[6.918731799],"iteration":993,"passed_time":1.410176243,"remaining_time":0.008512130242},
{"learn":[6.918328824],"iteration":994,"passed_time":1.411630768,"remaining_time":0.00709362195},
{"learn":[6.91825061],"iteration":995,"passed_time":1.413060659,"remaining_time":0.005674942406},
{"learn":[6.917721312],"iteration":996,"passed_time":1.414649192,"remaining_time":0.004256717728},
{"learn":[6.916899348],"iteration":997,"passed_time":1.41608586,"remaining_time":0.002837847416},
{"learn":[6.916819972],"iteration":998,"passed_time":1.417618916,"remaining_time":0.001419037954},
{"learn":[6.916507932],"iteration":999,"passed_time":1.419065048,"remaining_time":0}
]}